{"metadata": {"dataVersion": "2", "matchId": "EUW1_7890850146", "participants": ["yOI1CskHq3qMvY9lk0W7neCra2gpkzkCGa8P7szn6EXsybXh4tKIsBKp_yHyq7yz_GSQ0u3UFDcnAQ", "h1H1Bl-cUux8CMff9qdgJd1FTlxbolOkRxD7rPTQt2SV-169M4q0jlE73iRUgU0LkbPVhgeiVI9HUg", "30CdHMc490RdJTCIsKP4pTZr1fwXx2PkxKhwnGKXaB7ForXQb9n06342YvqjMIprGW9VR13eNW1WQg", "MiCdVKLsYhZX21jmdJbn1T22ytPyGsVJgWDTWfBJSq-5w0jAuazQwUATy1tYiR3Cqz1GO1LgVdpdjw", "WEvsU8k6rpVdGe-t-cb37_3_u3KjZPY6W_yLyavmW3aTQhb7sykqr-36LBiOZcJ06yihJwIw2n5p8g", "ZqH51cYbFoKHytcC04AW4QQEHKUQn3yPk-zB7lUPYKLuW0lwwRqBoJpi0cOrh7wBniWVSf_LrzvcUQ", "dfv_8GpGQuO4scvh-z1i0cyI-zRt54kYqBut64baWmF_Ltq2hZIV3X-0cm6Lz-OgySvSGRdXNfKzlQ", "ZGzDetUV02Pb018-5Lx34wsZE5N7eFzonCL1SR2I1r4qhsK72_l3xo9JhrhxoU-rrUbAjXQK_T6GEw", "fT29JLAIOS45Ni2ebQUZUannR8ndWP9lXx__YWLhGihIN_FDCk86nsPj_pFY38bLTWLEHTxfdRolmw", "f-rlectDTBi667BkmMQcuDBZf93Dc_yuNlMWbW8_GAHdxuEZEqsnTwJOjwZQRmj4_ccqXHQB4PGg3Q"]}, "info": {"endOfGameResult": "GameComplete", "gameCreation": 1781730945370, "gameDuration": 1712, "gameEndTimestamp": 1781732675340, "gameId": 7890850146, "gameMode": "CLASSIC", "gameName": "teambuilder-match-7890850146", "gameStartTimestamp": 1781730963528, "gameType": "MATCHED_GAME", "gameVersion": "16.12.788.4269", "mapId": 11, "participants": [{"PlayerBehavior": {"PlayerBehavior_IsHeroInCombat": 0}, "PlayerScore0": 0, "PlayerScore1": 0, "PlayerScore10": 0, "PlayerScore11": 0, "PlayerScore2": 0, "PlayerScore3": 0, "PlayerScore4": 0, "PlayerScore5": 0, "PlayerScore6": 0, "PlayerScore7": 0, "PlayerScore8": 0, "PlayerScore9": 0, "allInPings": 0, "assistMePings": 0, "assists": 4, "baronKills": 0, "basicPings": 0, "causedGameEndFromIGNBSurrender": false, "challenges": {"12AssistStreakCount": 0, "HealFromMapSources": 0, "InfernalScalePickup": 0, "SWARM_DefeatAatrox": 0, "SWARM_DefeatBriar": 0, "SWARM_DefeatMiniBosses": 0, "SWARM_EvolveWeapon": 0, "SWARM_Have3Passives": 0, "SWARM_KillEnemy": 0, "SWARM_PickupGold": 0, "SWARM_ReachLevel50": 0, "SWARM_Survive15Min": 0, "SWARM_WinWith5EvolvedWeapons": 0, "abilityUses": 84, "acesBefore15Minutes": 0, "alliedJungleMonsterKills": 0, "baronTakedowns": 0, "blastConeOppositeOpponentCount": 0, "bountyGold": 1381.7471923828125, "buffsStolen": 0, "completeSupportQuestInTime": 0, "controlWardTimeCoverageInRiverOrEnemyHalf": 0.7562346891637837, "controlWardsPlaced": 2, "damagePerMinute": 972.0289243957906, "damageTakenOnTeamPercentage": 0.27968131552220815, "dancedWithRiftHerald": 0, "deathsByEnemyChamps": 13, "dodgeSkillShotsSmallWindow": 0, "doubleAces": 0, "dragonTakedowns": 0, "earlyLaningPhaseGoldExpAdvantage": 0, "effectiveHealAndShielding": 0, "elderDragonKillsWithOpposingSoul": 0, "elderDragonMultikills": 0, "enemyChampionImmobilizations": 37, "enemyJungleMonsterKills": 0, "epicMonsterKillsNearEnemyJungler": 0, "epicMonsterKillsWithin30SecondsOfSpawn": 0, "epicMonsterSteals": 0, "epicMonsterStolenWithoutSmite": 0, "firstTurretKilled": 0, "fistBumpParticipation": 0, "flawlessAces": 0, "fullTeamTakedown": 0, "gameLength": 1712.120998711, "getTakedownsInAllLanesEarlyJungleAsLaner": 0, "goldPerMinute": 431.47479140634397, "hadOpenNexus": 0, "immobilizeAndKillWithAlly": 2, "initialBuffCount": 0, "initialCrabCount": 0, "jungleCsBefore10Minutes": 0, "junglerTakedownsNearDamagedEpicMonster": 0, "kTurretsDestroyedBeforePlatesFall": 0, "kda": 0.8461538461538461, "killAfterHiddenWithAlly": 0, "killParticipation": 0.6111111111111112, "killedChampTookFullTeamDamageSurvived": 0, "killingSprees": 1, "killsNearEnemyTurret": 4, "killsOnOtherLanesEarlyJungleAsLaner": 0, "killsOnRecentlyHealedByAramPack": 0, "killsUnderOwnTurret": 1, "killsWithHelpFromEpicMonster": 0, "knockEnemyIntoTeamAndKill": 0, "landSkillShotsEarlyGame": 0, "laneMinionsFirst10Minutes": 95, "laningPhaseGoldExpAdvantage": 0, "legendaryCount": 0, "legendaryItemUsed": [3153, 3087, 6631], "lostAnInhibitor": 0, "maxCsAdvantageOnLaneOpponent": 52, "maxKillDeficit": 0, "maxLevelLeadLaneOpponent": 1, "mejaisFullStackInTime": 0, "moreEnemyJungleThanOpponent": 0, "multiKillOneSpell": 0, "multiTurretRiftHeraldCount": 0, "multikills": 0, "multikillsAfterAggressiveFlash": 0, "outerTurretExecutesBefore10Minutes": 0, "outnumberedKills": 3, "outnumberedNexusKill": 0, "perfectDragonSoulsTaken": 0, "perfectGame": 0, "pickKillWithAlly": 5, "playedChampSelectPosition": 1, "poroExplosions": 0, "quickCleanse": 0, "quickFirstTurret": 0, "quickSoloKills": 0, "riftHeraldTakedowns": 0, "saveAllyFromDeath": 0, "scuttleCrabKills": 0, "skillshotsDodged": 17, "skillshotsHit": 0, "snowballsHit": 0, "soloBaronKills": 0, "soloKills": 4, "stealthWardsPlaced": 6, "survivedSingleDigitHpCount": 1, "survivedThreeImmobilizesInFight": 0, "takedownOnFirstTurret": 0, "takedowns": 11, "takedownsAfterGainingLevelAdvantage": 0, "takedownsBeforeJungleMinionSpawn": 0, "takedownsFirstXMinutes": 4, "takedownsInAlcove": 0, "takedownsInEnemyFountain": 0, "teamBaronKills": 0, "teamDamagePercentage": 0.3136511452578549, "teamElderDragonKills": 0, "teamRiftHeraldKills": 1, "tookLargeDamageSurvived": 0, "turretPlatesTaken": 4, "turretTakedowns": 1, "turretsTakenWithRiftHerald": 0, "twentyMinionsIn3SecondsCount": 0, "twoWardsOneSweeperCount": 0, "unseenRecalls": 0, "visionScoreAdvantageLaneOpponent": 0.37097370624542236, "visionScorePerMinute": 0.9176494986020461, "voidMonsterKill": 0, "wardTakedowns": 0, "wardTakedownsBefore20M": 0, "wardsGuarded": 0}, "champExperience": 15284, "champLevel": 16, "championId": 19, "championName": "Warwick", "championTransform": 0, "commandPings": 1, "consumablesPurchased": 5, "damageDealtToBuildings": 3946, "damageDealtToEpicMonsters": 0, "damageDealtToObjectives": 3946, "damageDealtToTurrets": 3946, "damageSelfMitigated": 39289, "dangerPings": 0, "deaths": 13, "detectorWardsPlaced": 2, "doubleKills": 0, "dragonKills": 0, "eligibleForProgression": true, "enemyMissingPings": 0, "enemyVisionPings": 0, "firstBloodAssist": false, "firstBloodKill": false, "firstTowerAssist": false, "firstTowerKill": false, "gameEndedInEarlySurrender": false, "gameEndedInIGNBSurrender": false, "gameEndedInSurrender": false, "getBackPings": 0, "goldEarned": 12312, "goldSpent": 11700, "holdPings": 0, "individualPosition": "TOP", "inhibitorKills": 0, "inhibitorTakedowns": 0, "inhibitorsLost": 4, "item0": 1086, "item1": 6631, "item2": 3087, "item3": 3047, "item4": 1029, "item5": 3153, "item6": 3340, "itemsPurchased": 26, "killingSprees": 1, "kills": 7, "lane": "JUNGLE", "largestCriticalStrike": 0, "largestKillingSpree": 3, "largestMultiKill": 1, "longestTimeSpentLiving": 658, "magicDamageDealt": 41278, "magicDamageDealtToChampions": 12862, "magicDamageTaken": 17606, "missions": {"playerScore0": 0, "playerScore1": 0, "playerScore2": 0, "playerScore3": 0, "playerScore4": 0, "playerScore5": 0, "playerScore6": 0, "playerScore7": 0, "playerScore8": 0, "playerScore9": 0, "playerScore10": 0, "playerScore11": 0}, "needVisionPings": 0, "neutralMinionsKilled": 0, "nexusKills": 0, "nexusLost": 1, "nexusTakedowns": 0, "objectivesStolen": 0, "objectivesStolenAssists": 0, "onMyWayPings": 0, "participantId": 1, "pentaKills": 0, "perks": {"statPerks": {"defense": 5001, "flex": 5008, "offense": 5005}, "styles": [{"description": "primaryStyle", "selections": [{"perk": 8008, "var1": 1738, "var2": 1738, "var3": 0}, {"perk": 8009, "var1": 1290, "var2": 0, "var3": 0}, {"perk": 9104, "var1": 17, "var2": 30, "var3": 0}, {"perk": 8299, "var1": 2406, "var2": 0, "var3": 0}], "style": 8000}, {"description": "subStyle", "selections": [{"perk": 8473, "var1": 1135, "var2": 0, "var3": 0}, {"perk": 8453, "var1": 1618, "var2": 274, "var3": 0}], "style": 8400}]}, "physicalDamageDealt": 87064, "physicalDamageDealtToChampions": 14874, "physicalDamageTaken": 24141, "placement": 0, "playerAugment1": 0, "playerAugment2": 0, "playerAugment3": 0, "playerAugment4": 0, "playerAugment5": 0, "playerAugment6": 0, "playerSubteamId": 0, "positionAssignedByMatchmaking": "TOP", "profileIcon": 6219, "pushPings": 0, "puuid": "yOI1CskHq3qMvY9lk0W7neCra2gpkzkCGa8P7szn6EXsybXh4tKIsBKp_yHyq7yz_GSQ0u3UFDcnAQ", "quadraKills": 0, "retreatPings": 0, "riotIdGameName": "TopNotch", "riotIdTagline": "888", "role": "NONE", "roleBoundItem": 1220, "selectedRolePreferences": "TOP.PRIMARY.TOP.JUNGLE", "sightWardsBoughtInGame": 0, "spell1Casts": 32, "spell2Casts": 8, "spell3Casts": 36, "spell4Casts": 8, "subteamPlacement": 0, "summoner1Casts": 6, "summoner1Id": 21, "summoner2Casts": 3, "summoner2Id": 4, "summonerId": "uUpmg7-xF4qPkIFt_eZ9MNFLCCOrXkHafBp21UC_u-IESA0", "summonerLevel": 835, "summonerName": "", "teamEarlySurrendered": false, "teamIGNBSurrendered": false, "teamId": 100, "teamPosition": "TOP", "timeCCingOthers": 40, "timePlayed": 1712, "totalAllyJungleMinionsKilled": 0, "totalDamageDealt": 129627, "totalDamageDealtToChampions": 27737, "totalDamageShieldedOnTeammates": 0, "totalDamageTaken": 42624, "totalEnemyJungleMinionsKilled": 0, "totalHeal": 14564, "totalHealsOnTeammates": 0, "totalMinionsKilled": 180, "totalTimeCCDealt": 137, "totalTimeSpentDead": 473, "totalUnitsHealed": 1, "tripleKills": 0, "trueDamageDealt": 1284, "trueDamageDealtToChampions": 0, "trueDamageTaken": 875, "turretKills": 1, "turretTakedowns": 1, "turretsLost": 13, "unrealKills": 0, "visionClearedPings": 0, "visionScore": 26, "visionWardsBoughtInGame": 2, "wardsKilled": 0, "wardsPlaced": 8, "wasPremadeWithIGNBGameEndCauser": false, "wasPremadeWithSevereTransgressor": false, "wasSevereTransgressor": false, "win": false}, {"PlayerBehavior": {"PlayerBehavior_IsHeroInCombat": 0}, "PlayerScore0": 0, "PlayerScore1": 0, "PlayerScore10": 0, "PlayerScore11": 0, "PlayerScore2": 0, "PlayerScore3": 0, "PlayerScore4": 0, "PlayerScore5": 0, "PlayerScore6": 0, "PlayerScore7": 0, "PlayerScore8": 0, "PlayerScore9": 0, "allInPings": 0, "assistMePings": 3, "assists": 5, "baronKills": 0, "basicPings": 0, "causedGameEndFromIGNBSurrender": false, "challenges": {"12AssistStreakCount": 0, "HealFromMapSources": 186, "InfernalScalePickup": 0, "SWARM_DefeatAatrox": 0, "SWARM_DefeatBriar": 0, "SWARM_DefeatMiniBosses": 0, "SWARM_EvolveWeapon": 0, "SWARM_Have3Passives": 0, "SWARM_KillEnemy": 0, "SWARM_PickupGold": 0, "SWARM_ReachLevel50": 0, "SWARM_Survive15Min": 0, "SWARM_WinWith5EvolvedWeapons": 0, "abilityUses": 272, "acesBefore15Minutes": 0, "alliedJungleMonsterKills": 65, "baronTakedowns": 0, "blastConeOppositeOpponentCount": 0, "bountyGold": 2008.8258666992188, "buffsStolen": 0, "completeSupportQuestInTime": 0, "controlWardsPlaced": 0, "damagePerMinute": 492.1124358562175, "damageTakenOnTeamPercentage": 0.20388906158592887, "dancedWithRiftHerald": 0, "deathsByEnemyChamps": 8, "dodgeSkillShotsSmallWindow": 0, "doubleAces": 0, "dragonTakedowns": 0, "earlyLaningPhaseGoldExpAdvantage": 0, "effectiveHealAndShielding": 0, "elderDragonKillsWithOpposingSoul": 0, "elderDragonMultikills": 0, "enemyChampionImmobilizations": 11, "enemyJungleMonsterKills": 0, "epicMonsterKillsNearEnemyJungler": 0, "epicMonsterKillsWithin30SecondsOfSpawn": 0, "epicMonsterSteals": 0, "epicMonsterStolenWithoutSmite": 0, "firstTurretKilled": 0, "fistBumpParticipation": 0, "flawlessAces": 0, "fullTeamTakedown": 0, "gameLength": 1712.120998711, "goldPerMinute": 442.0726318451392, "hadOpenNexus": 0, "immobilizeAndKillWithAlly": 3, "initialBuffCount": 1, "initialCrabCount": 0, "jungleCsBefore10Minutes": 52.00000008940697, "junglerKillsEarlyJungle": 0, "junglerTakedownsNearDamagedEpicMonster": 0, "kTurretsDestroyedBeforePlatesFall": 0, "kda": 1.25, "killAfterHiddenWithAlly": 1, "killParticipation": 0.5555555555555556, "killedChampTookFullTeamDamageSurvived": 0, "killingSprees": 0, "killsNearEnemyTurret": 0, "killsOnLanersEarlyJungleAsJungler": 1, "killsOnRecentlyHealedByAramPack": 0, "killsUnderOwnTurret": 1, "killsWithHelpFromEpicMonster": 0, "knockEnemyIntoTeamAndKill": 0, "landSkillShotsEarlyGame": 0, "laneMinionsFirst10Minutes": 0, "laningPhaseGoldExpAdvantage": 0, "legendaryCount": 0, "legendaryItemUsed": [6692, 3071, 6333], "lostAnInhibitor": 0, "maxCsAdvantageOnLaneOpponent": 4.500000029802322, "maxKillDeficit": 0, "maxLevelLeadLaneOpponent": 1, "mejaisFullStackInTime": 0, "moreEnemyJungleThanOpponent": -53.00000008940697, "multiKillOneSpell": 0, "multiTurretRiftHeraldCount": 0, "multikills": 0, "multikillsAfterAggressiveFlash": 0, "outerTurretExecutesBefore10Minutes": 0, "outnumberedKills": 1, "outnumberedNexusKill": 0, "perfectDragonSoulsTaken": 0, "perfectGame": 0, "pickKillWithAlly": 8, "playedChampSelectPosition": 1, "poroExplosions": 0, "quickCleanse": 0, "quickFirstTurret": 0, "quickSoloKills": 0, "riftHeraldTakedowns": 1, "saveAllyFromDeath": 0, "scuttleCrabKills": 1, "skillshotsDodged": 22, "skillshotsHit": 0, "snowballsHit": 0, "soloBaronKills": 0, "soloKills": 1, "stealthWardsPlaced": 11, "survivedSingleDigitHpCount": 0, "survivedThreeImmobilizesInFight": 0, "takedownOnFirstTurret": 0, "takedowns": 10, "takedownsAfterGainingLevelAdvantage": 0, "takedownsBeforeJungleMinionSpawn": 0, "takedownsFirstXMinutes": 4, "takedownsInAlcove": 1, "takedownsInEnemyFountain": 0, "teamBaronKills": 0, "teamDamagePercentage": 0.15879324701976297, "teamElderDragonKills": 0, "teamRiftHeraldKills": 1, "tookLargeDamageSurvived": 0, "turretPlatesTaken": 3, "turretTakedowns": 0, "turretsTakenWithRiftHerald": 0, "twentyMinionsIn3SecondsCount": 0, "twoWardsOneSweeperCount": 0, "unseenRecalls": 0, "visionScoreAdvantageLaneOpponent": -0.23242592811584473, "visionScorePerMinute": 0.8312011100653764, "voidMonsterKill": 5, "wardTakedowns": 1, "wardTakedownsBefore20M": 1, "wardsGuarded": 0}, "champExperience": 12202, "champLevel": 14, "championId": 141, "championName": "Kayn", "championTransform": 1, "commandPings": 2, "consumablesPurchased": 0, "damageDealtToBuildings": 4554, "damageDealtToEpicMonsters": 23448, "damageDealtToObjectives": 28003, "damageDealtToTurrets": 4554, "damageSelfMitigated": 35517, "dangerPings": 0, "deaths": 8, "detectorWardsPlaced": 0, "doubleKills": 0, "dragonKills": 0, "eligibleForProgression": true, "enemyMissingPings": 0, "enemyVisionPings": 0, "firstBloodAssist": false, "firstBloodKill": false, "firstTowerAssist": false, "firstTowerKill": false, "gameEndedInEarlySurrender": false, "gameEndedInIGNBSurrender": false, "gameEndedInSurrender": false, "getBackPings": 0, "goldEarned": 12614, "goldSpent": 12250, "holdPings": 0, "individualPosition": "JUNGLE", "inhibitorKills": 0, "inhibitorTakedowns": 0, "inhibitorsLost": 4, "item0": 6692, "item1": 3071, "item2": 6333, "item3": 3133, "item4": 1036, "item5": 3047, "item6": 3340, "itemsPurchased": 19, "killingSprees": 0, "kills": 5, "lane": "JUNGLE", "largestCriticalStrike": 0, "largestKillingSpree": 0, "largestMultiKill": 1, "longestTimeSpentLiving": 384, "magicDamageDealt": 0, "magicDamageDealtToChampions": 0, "magicDamageTaken": 10304, "missions": {"playerScore0": 0, "playerScore1": 0, "playerScore2": 0, "playerScore3": 0, "playerScore4": 0, "playerScore5": 0, "playerScore6": 0, "playerScore7": 0, "playerScore8": 0, "playerScore9": 0, "playerScore10": 0, "playerScore11": 0}, "needVisionPings": 0, "neutralMinionsKilled": 112, "nexusKills": 0, "nexusLost": 1, "nexusTakedowns": 0, "objectivesStolen": 0, "objectivesStolenAssists": 0, "onMyWayPings": 4, "participantId": 2, "pentaKills": 0, "perks": {"statPerks": {"defense": 5001, "flex": 5008, "offense": 5008}, "styles": [{"description": "primaryStyle", "selections": [{"perk": 8010, "var1": 110, "var2": 0, "var3": 0}, {"perk": 9111, "var1": 651, "var2": 200, "var3": 0}, {"perk": 9105, "var1": 13, "var2": 0, "var3": 0}, {"perk": 8299, "var1": 1224, "var2": 0, "var3": 0}], "style": 8000}, {"description": "subStyle", "selections": [{"perk": 8224, "var1": 30, "var2": 799, "var3": 0}, {"perk": 8210, "var1": 9, "var2": 0, "var3": 0}], "style": 8200}]}, "physicalDamageDealt": 127580, "physicalDamageDealtToChampions": 13749, "physicalDamageTaken": 18809, "placement": 0, "playerAugment1": 0, "playerAugment2": 0, "playerAugment3": 0, "playerAugment4": 0, "playerAugment5": 0, "playerAugment6": 0, "playerSubteamId": 0, "positionAssignedByMatchmaking": "JUNGLE", "profileIcon": 5982, "pushPings": 0, "puuid": "h1H1Bl-cUux8CMff9qdgJd1FTlxbolOkRxD7rPTQt2SV-169M4q0jlE73iRUgU0LkbPVhgeiVI9HUg", "quadraKills": 0, "retreatPings": 0, "riotIdGameName": "krisss", "riotIdTagline": "222", "role": "NONE", "roleBoundItem": 1209, "selectedRolePreferences": "JUNGLE.PRIMARY.JUNGLE.UTILITY", "sightWardsBoughtInGame": 0, "spell1Casts": 152, "spell2Casts": 65, "spell3Casts": 41, "spell4Casts": 14, "subteamPlacement": 0, "summoner1Casts": 4, "summoner1Id": 4, "summoner2Casts": 14, "summoner2Id": 11, "summonerId": "zDENem1EmYTSBhmA7rU0tmM_gkSwvNAffWj7Z9-j2LM-dVxfIH0Gkl8zrw", "summonerLevel": 795, "summonerName": "", "teamEarlySurrendered": false, "teamIGNBSurrendered": false, "teamId": 100, "teamPosition": "JUNGLE", "timeCCingOthers": 16, "timePlayed": 1712, "totalAllyJungleMinionsKilled": 92, "totalDamageDealt": 196028, "totalDamageDealtToChampions": 14042, "totalDamageShieldedOnTeammates": 0, "totalDamageTaken": 31073, "totalEnemyJungleMinionsKilled": 0, "totalHeal": 12089, "totalHealsOnTeammates": 0, "totalMinionsKilled": 35, "totalTimeCCDealt": 288, "totalTimeSpentDead": 201, "totalUnitsHealed": 1, "tripleKills": 0, "trueDamageDealt": 68448, "trueDamageDealtToChampions": 292, "trueDamageTaken": 1958, "turretKills": 0, "turretTakedowns": 0, "turretsLost": 13, "unrealKills": 0, "visionClearedPings": 0, "visionScore": 23, "visionWardsBoughtInGame": 0, "wardsKilled": 1, "wardsPlaced": 11, "wasPremadeWithIGNBGameEndCauser": false, "wasPremadeWithSevereTransgressor": false, "wasSevereTransgressor": false, "win": false}, {"PlayerBehavior": {"PlayerBehavior_IsHeroInCombat": 0}, "PlayerScore0": 0, "PlayerScore1": 0, "PlayerScore10": 0, "PlayerScore11": 0, "PlayerScore2": 0, "PlayerScore3": 0, "PlayerScore4": 0, "PlayerScore5": 0, "PlayerScore6": 0, "PlayerScore7": 0, "PlayerScore8": 0, "PlayerScore9": 0, "allInPings": 1, "assistMePings": 0, "assists": 3, "baronKills": 0, "basicPings": 0, "causedGameEndFromIGNBSurrender": false, "challenges": {"12AssistStreakCount": 0, "HealFromMapSources": 0, "InfernalScalePickup": 0, "SWARM_DefeatAatrox": 0, "SWARM_DefeatBriar": 0, "SWARM_DefeatMiniBosses": 0, "SWARM_EvolveWeapon": 0, "SWARM_Have3Passives": 0, "SWARM_KillEnemy": 0, "SWARM_PickupGold": 0, "SWARM_ReachLevel50": 0, "SWARM_Survive15Min": 0, "SWARM_WinWith5EvolvedWeapons": 0, "abilityUses": 405, "acesBefore15Minutes": 0, "alliedJungleMonsterKills": 0, "baronTakedowns": 0, "blastConeOppositeOpponentCount": 0, "bountyGold": 134.87632751464844, "buffsStolen": 0, "completeSupportQuestInTime": 0, "controlWardsPlaced": 0, "damagePerMinute": 797.520800459199, "damageTakenOnTeamPercentage": 0.15172864468388275, "dancedWithRiftHerald": 0, "deathsByEnemyChamps": 9, "dodgeSkillShotsSmallWindow": 0, "doubleAces": 0, "dragonTakedowns": 0, "earlyLaningPhaseGoldExpAdvantage": 0, "effectiveHealAndShielding": 0, "elderDragonKillsWithOpposingSoul": 0, "elderDragonMultikills": 0, "enemyChampionImmobilizations": 9, "enemyJungleMonsterKills": 0, "epicMonsterKillsNearEnemyJungler": 0, "epicMonsterKillsWithin30SecondsOfSpawn": 0, "epicMonsterSteals": 0, "epicMonsterStolenWithoutSmite": 0, "firstTurretKilled": 0, "fistBumpParticipation": 0, "flawlessAces": 0, "fullTeamTakedown": 0, "gameLength": 1712.120998711, "getTakedownsInAllLanesEarlyJungleAsLaner": 0, "goldPerMinute": 417.51482458055045, "hadOpenNexus": 0, "immobilizeAndKillWithAlly": 3, "initialBuffCount": 0, "initialCrabCount": 0, "jungleCsBefore10Minutes": 2, "junglerTakedownsNearDamagedEpicMonster": 0, "kTurretsDestroyedBeforePlatesFall": 0, "kda": 0.6666666666666666, "killAfterHiddenWithAlly": 0, "killParticipation": 0.3333333333333333, "killedChampTookFullTeamDamageSurvived": 0, "killingSprees": 0, "killsNearEnemyTurret": 0, "killsOnOtherLanesEarlyJungleAsLaner": 0, "killsOnRecentlyHealedByAramPack": 0, "killsUnderOwnTurret": 1, "killsWithHelpFromEpicMonster": 0, "knockEnemyIntoTeamAndKill": 0, "landSkillShotsEarlyGame": 0, "laneMinionsFirst10Minutes": 71, "laningPhaseGoldExpAdvantage": 0, "legendaryCount": 0, "legendaryItemUsed": [2503, 3116, 6653], "lostAnInhibitor": 0, "maxCsAdvantageOnLaneOpponent": 91, "maxKillDeficit": 0, "maxLevelLeadLaneOpponent": 2, "mejaisFullStackInTime": 0, "moreEnemyJungleThanOpponent": 0, "multiKillOneSpell": 0, "multiTurretRiftHeraldCount": 0, "multikills": 0, "multikillsAfterAggressiveFlash": 0, "outerTurretExecutesBefore10Minutes": 0, "outnumberedKills": 1, "outnumberedNexusKill": 0, "perfectDragonSoulsTaken": 0, "perfectGame": 0, "pickKillWithAlly": 4, "playedChampSelectPosition": 1, "poroExplosions": 0, "quickCleanse": 0, "quickFirstTurret": 0, "quickSoloKills": 0, "riftHeraldTakedowns": 0, "saveAllyFromDeath": 0, "scuttleCrabKills": 0, "skillshotsDodged": 20, "skillshotsHit": 0, "snowballsHit": 0, "soloBaronKills": 0, "soloKills": 0, "stealthWardsPlaced": 5, "survivedSingleDigitHpCount": 0, "survivedThreeImmobilizesInFight": 0, "takedownOnFirstTurret": 0, "takedowns": 6, "takedownsAfterGainingLevelAdvantage": 0, "takedownsBeforeJungleMinionSpawn": 0, "takedownsFirstXMinutes": 0, "takedownsInAlcove": 0, "takedownsInEnemyFountain": 0, "teamBaronKills": 0, "teamDamagePercentage": 0.25734142899757545, "teamElderDragonKills": 0, "teamRiftHeraldKills": 1, "tookLargeDamageSurvived": 0, "turretPlatesTaken": 4, "turretTakedowns": 1, "turretsTakenWithRiftHerald": 0, "twentyMinionsIn3SecondsCount": 0, "twoWardsOneSweeperCount": 0, "unseenRecalls": 0, "visionScoreAdvantageLaneOpponent": -0.38896459341049194, "visionScorePerMinute": 0.3812515892670882, "voidMonsterKill": 3, "wardTakedowns": 0, "wardTakedownsBefore20M": 0, "wardsGuarded": 0}, "champExperience": 17036, "champLevel": 17, "championId": 90, "championName": "Malzahar", "championTransform": 0, "commandPings": 0, "consumablesPurchased": 4, "damageDealtToBuildings": 2880, "damageDealtToEpicMonsters": 1796, "damageDealtToObjectives": 4677, "damageDealtToTurrets": 2880, "damageSelfMitigated": 16926, "dangerPings": 0, "deaths": 9, "detectorWardsPlaced": 0, "doubleKills": 0, "dragonKills": 0, "eligibleForProgression": true, "enemyMissingPings": 1, "enemyVisionPings": 5, "firstBloodAssist": false, "firstBloodKill": false, "firstTowerAssist": false, "firstTowerKill": false, "gameEndedInEarlySurrender": false, "gameEndedInIGNBSurrender": false, "gameEndedInSurrender": false, "getBackPings": 0, "goldEarned": 11913, "goldSpent": 10850, "holdPings": 0, "individualPosition": "MIDDLE", "inhibitorKills": 0, "inhibitorTakedowns": 0, "inhibitorsLost": 4, "item0": 2503, "item1": 3175, "item2": 3116, "item3": 6653, "item4": 3108, "item5": 0, "item6": 3340, "itemsPurchased": 21, "killingSprees": 1, "kills": 3, "lane": "MIDDLE", "largestCriticalStrike": 0, "largestKillingSpree": 2, "largestMultiKill": 1, "longestTimeSpentLiving": 415, "magicDamageDealt": 206251, "magicDamageDealtToChampions": 22481, "magicDamageTaken": 7396, "missions": {"playerScore0": 0, "playerScore1": 0, "playerScore2": 0, "playerScore3": 0, "playerScore4": 0, "playerScore5": 0, "playerScore6": 0, "playerScore7": 0, "playerScore8": 0, "playerScore9": 0, "playerScore10": 0, "playerScore11": 0}, "needVisionPings": 0, "neutralMinionsKilled": 2, "nexusKills": 0, "nexusLost": 1, "nexusTakedowns": 0, "objectivesStolen": 0, "objectivesStolenAssists": 0, "onMyWayPings": 4, "participantId": 3, "pentaKills": 0, "perks": {"statPerks": {"defense": 5001, "flex": 5008, "offense": 5008}, "styles": [{"description": "primaryStyle", "selections": [{"perk": 8992, "var1": 1918, "var2": 0, "var3": 0}, {"perk": 8226, "var1": 250, "var2": 931, "var3": 0}, {"perk": 8210, "var1": 8, "var2": 0, "var3": 0}, {"perk": 8236, "var1": 24, "var2": 0, "var3": 0}], "style": 8200}, {"description": "subStyle", "selections": [{"perk": 8009, "var1": 2038, "var2": 0, "var3": 0}, {"perk": 9105, "var1": 18, "var2": 40, "var3": 0}], "style": 8000}]}, "physicalDamageDealt": 6888, "physicalDamageDealtToChampions": 275, "physicalDamageTaken": 14940, "placement": 0, "playerAugment1": 0, "playerAugment2": 0, "playerAugment3": 0, "playerAugment4": 0, "playerAugment5": 0, "playerAugment6": 0, "playerSubteamId": 0, "positionAssignedByMatchmaking": "MIDDLE", "profileIcon": 907, "pushPings": 0, "puuid": "30CdHMc490RdJTCIsKP4pTZr1fwXx2PkxKhwnGKXaB7ForXQb9n06342YvqjMIprGW9VR13eNW1WQg", "quadraKills": 0, "retreatPings": 0, "riotIdGameName": "THESQUATMASTER", "riotIdTagline": "EUW", "role": "SOLO", "roleBoundItem": 1206, "selectedRolePreferences": "MIDDLE.PRIMARY.MIDDLE.JUNGLE", "sightWardsBoughtInGame": 0, "spell1Casts": 125, "spell2Casts": 152, "spell3Casts": 117, "spell4Casts": 11, "subteamPlacement": 0, "summoner1Casts": 3, "summoner1Id": 12, "summoner2Casts": 4, "summoner2Id": 4, "summonerId": "r_vMomW_X4PKGqBFRlelusm4VfvFF1HDfdZquM783C3KWYC_4ZKGUd4p_g", "summonerLevel": 68, "summonerName": "", "teamEarlySurrendered": false, "teamIGNBSurrendered": false, "teamId": 100, "teamPosition": "MIDDLE", "timeCCingOthers": 52, "timePlayed": 1712, "totalAllyJungleMinionsKilled": 0, "totalDamageDealt": 226630, "totalDamageDealtToChampions": 22757, "totalDamageShieldedOnTeammates": 0, "totalDamageTaken": 23123, "totalEnemyJungleMinionsKilled": 0, "totalHeal": 684, "totalHealsOnTeammates": 0, "totalMinionsKilled": 275, "totalTimeCCDealt": 725, "totalTimeSpentDead": 247, "totalUnitsHealed": 1, "tripleKills": 0, "trueDamageDealt": 13490, "trueDamageDealtToChampions": 0, "trueDamageTaken": 786, "turretKills": 0, "turretTakedowns": 1, "turretsLost": 13, "unrealKills": 0, "visionClearedPings": 0, "visionScore": 10, "visionWardsBoughtInGame": 0, "wardsKilled": 0, "wardsPlaced": 5, "wasPremadeWithIGNBGameEndCauser": false, "wasPremadeWithSevereTransgressor": false, "wasSevereTransgressor": false, "win": false}, {"PlayerBehavior": {"PlayerBehavior_IsHeroInCombat": 0}, "PlayerScore0": 0, "PlayerScore1": 0, "PlayerScore10": 0, "PlayerScore11": 0, "PlayerScore2": 0, "PlayerScore3": 0, "PlayerScore4": 0, "PlayerScore5": 0, "PlayerScore6": 0, "PlayerScore7": 0, "PlayerScore8": 0, "PlayerScore9": 0, "allInPings": 0, "assistMePings": 0, "assists": 5, "baronKills": 0, "basicPings": 0, "causedGameEndFromIGNBSurrender": false, "challenges": {"12AssistStreakCount": 0, "HealFromMapSources": 0, "InfernalScalePickup": 0, "SWARM_DefeatAatrox": 0, "SWARM_DefeatBriar": 0, "SWARM_DefeatMiniBosses": 0, "SWARM_EvolveWeapon": 0, "SWARM_Have3Passives": 0, "SWARM_KillEnemy": 0, "SWARM_PickupGold": 0, "SWARM_ReachLevel50": 0, "SWARM_Survive15Min": 0, "SWARM_WinWith5EvolvedWeapons": 0, "abilityUses": 175, "acesBefore15Minutes": 0, "alliedJungleMonsterKills": 0, "baronTakedowns": 0, "blastConeOppositeOpponentCount": 0, "bountyGold": 0, "buffsStolen": 0, "completeSupportQuestInTime": 0, "controlWardsPlaced": 0, "damagePerMinute": 338.5013979729402, "damageTakenOnTeamPercentage": 0.20121061849622207, "dancedWithRiftHerald": 0, "deathsByEnemyChamps": 21, "dodgeSkillShotsSmallWindow": 0, "doubleAces": 0, "dragonTakedowns": 0, "earlyLaningPhaseGoldExpAdvantage": 0, "effectiveHealAndShielding": 0, "elderDragonKillsWithOpposingSoul": 0, "elderDragonMultikills": 0, "enemyChampionImmobilizations": 8, "enemyJungleMonsterKills": 0, "epicMonsterKillsNearEnemyJungler": 0, "epicMonsterKillsWithin30SecondsOfSpawn": 0, "epicMonsterSteals": 0, "epicMonsterStolenWithoutSmite": 0, "firstTurretKilled": 0, "fistBumpParticipation": 0, "flawlessAces": 0, "fullTeamTakedown": 0, "gameLength": 1712.120998711, "getTakedownsInAllLanesEarlyJungleAsLaner": 0, "goldPerMinute": 225.91663871008916, "hadOpenNexus": 0, "immobilizeAndKillWithAlly": 1, "initialBuffCount": 0, "initialCrabCount": 0, "jungleCsBefore10Minutes": 0, "junglerTakedownsNearDamagedEpicMonster": 0, "kTurretsDestroyedBeforePlatesFall": 0, "kda": 0.23809523809523808, "killAfterHiddenWithAlly": 1, "killParticipation": 0.2777777777777778, "killedChampTookFullTeamDamageSurvived": 0, "killingSprees": 0, "killsNearEnemyTurret": 0, "killsOnOtherLanesEarlyJungleAsLaner": 0, "killsOnRecentlyHealedByAramPack": 0, "killsUnderOwnTurret": 0, "killsWithHelpFromEpicMonster": 0, "knockEnemyIntoTeamAndKill": 1, "landSkillShotsEarlyGame": 14, "laneMinionsFirst10Minutes": 14, "laningPhaseGoldExpAdvantage": 0, "legendaryCount": 0, "legendaryItemUsed": [6655, 4628], "lostAnInhibitor": 0, "maxCsAdvantageOnLaneOpponent": 0, "maxKillDeficit": 0, "maxLevelLeadLaneOpponent": 0, "mejaisFullStackInTime": 0, "moreEnemyJungleThanOpponent": 0, "multiKillOneSpell": 0, "multiTurretRiftHeraldCount": 0, "multikills": 0, "multikillsAfterAggressiveFlash": 0, "outerTurretExecutesBefore10Minutes": 0, "outnumberedKills": 0, "outnumberedNexusKill": 0, "perfectDragonSoulsTaken": 0, "perfectGame": 0, "pickKillWithAlly": 4, "playedChampSelectPosition": 1, "poroExplosions": 0, "quickCleanse": 0, "quickFirstTurret": 0, "quickSoloKills": 0, "riftHeraldTakedowns": 0, "saveAllyFromDeath": 0, "scuttleCrabKills": 0, "skillshotsDodged": 28, "skillshotsHit": 53, "snowballsHit": 0, "soloBaronKills": 0, "soloKills": 0, "stealthWardsPlaced": 9, "survivedSingleDigitHpCount": 0, "survivedThreeImmobilizesInFight": 0, "takedownOnFirstTurret": 0, "takedowns": 5, "takedownsAfterGainingLevelAdvantage": 0, "takedownsBeforeJungleMinionSpawn": 0, "takedownsFirstXMinutes": 1, "takedownsInAlcove": 0, "takedownsInEnemyFountain": 0, "teamBaronKills": 0, "teamDamagePercentage": 0.10922653480871808, "teamElderDragonKills": 0, "teamRiftHeraldKills": 1, "tookLargeDamageSurvived": 0, "turretPlatesTaken": 0, "turretTakedowns": 0, "turretsTakenWithRiftHerald": 0, "twentyMinionsIn3SecondsCount": 0, "twoWardsOneSweeperCount": 0, "unseenRecalls": 0, "visionScoreAdvantageLaneOpponent": -0.2184491753578186, "visionScorePerMinute": 0.5431097758245487, "voidMonsterKill": 0, "wardTakedowns": 0, "wardTakedownsBefore20M": 0, "wardsGuarded": 0}, "champExperience": 11147, "champLevel": 13, "championId": 115, "championName": "Ziggs", "championTransform": 0, "commandPings": 0, "consumablesPurchased": 4, "damageDealtToBuildings": 0, "damageDealtToEpicMonsters": 53, "damageDealtToObjectives": 53, "damageDealtToTurrets": 0, "damageSelfMitigated": 11451, "dangerPings": 0, "deaths": 21, "detectorWardsPlaced": 0, "doubleKills": 0, "dragonKills": 0, "eligibleForProgression": true, "enemyMissingPings": 2, "enemyVisionPings": 0, "firstBloodAssist": false, "firstBloodKill": false, "firstTowerAssist": false, "firstTowerKill": false, "gameEndedInEarlySurrender": false, "gameEndedInIGNBSurrender": false, "gameEndedInSurrender": false, "getBackPings": 8, "goldEarned": 6446, "goldSpent": 6050, "holdPings": 0, "individualPosition": "BOTTOM", "inhibitorKills": 0, "inhibitorTakedowns": 0, "inhibitorsLost": 4, "item0": 2003, "item1": 6655, "item2": 4628, "item3": 3070, "item4": 0, "item5": 0, "item6": 3340, "itemsPurchased": 20, "killingSprees": 0, "kills": 0, "lane": "BOTTOM", "largestCriticalStrike": 0, "largestKillingSpree": 0, "largestMultiKill": 0, "longestTimeSpentLiving": 173, "magicDamageDealt": 59087, "magicDamageDealtToChampions": 9145, "magicDamageTaken": 16655, "missions": {"playerScore0": 0, "playerScore1": 0, "playerScore2": 0, "playerScore3": 0, "playerScore4": 0, "playerScore5": 0, "playerScore6": 0, "playerScore7": 0, "playerScore8": 0, "playerScore9": 0, "playerScore10": 0, "playerScore11": 0}, "needVisionPings": 0, "neutralMinionsKilled": 0, "nexusKills": 0, "nexusLost": 1, "nexusTakedowns": 0, "objectivesStolen": 0, "objectivesStolenAssists": 0, "onMyWayPings": 0, "participantId": 4, "pentaKills": 0, "perks": {"statPerks": {"defense": 5001, "flex": 5008, "offense": 5008}, "styles": [{"description": "primaryStyle", "selections": [{"perk": 8229, "var1": 602, "var2": 0, "var3": 0}, {"perk": 8226, "var1": 250, "var2": 527, "var3": 0}, {"perk": 8210, "var1": 2, "var2": 0, "var3": 0}, {"perk": 8237, "var1": 432, "var2": 0, "var3": 0}], "style": 8200}, {"description": "subStyle", "selections": [{"perk": 8014, "var1": 191, "var2": 0, "var3": 0}, {"perk": 8009, "var1": 1314, "var2": 0, "var3": 0}], "style": 8000}]}, "physicalDamageDealt": 4606, "physicalDamageDealtToChampions": 514, "physicalDamageTaken": 13061, "placement": 0, "playerAugment1": 0, "playerAugment2": 0, "playerAugment3": 0, "playerAugment4": 0, "playerAugment5": 0, "playerAugment6": 0, "playerSubteamId": 0, "positionAssignedByMatchmaking": "BOTTOM", "profileIcon": 4764, "pushPings": 0, "puuid": "MiCdVKLsYhZX21jmdJbn1T22ytPyGsVJgWDTWfBJSq-5w0jAuazQwUATy1tYiR3Cqz1GO1LgVdpdjw", "quadraKills": 0, "retreatPings": 1, "riotIdGameName": "daevaking", "riotIdTagline": "EUW", "role": "DUO", "roleBoundItem": 1207, "selectedRolePreferences": "BOTTOM.PRIMARY.BOTTOM.UTILITY.FILL", "sightWardsBoughtInGame": 0, "spell1Casts": 91, "spell2Casts": 37, "spell3Casts": 41, "spell4Casts": 6, "subteamPlacement": 0, "summoner1Casts": 5, "summoner1Id": 4, "summoner2Casts": 1, "summoner2Id": 12, "summonerId": "gwXYytsPYNHc_nRLE81zze3UZw_Md66675jGET9cJ00Fmp4", "summonerLevel": 84, "summonerName": "", "teamEarlySurrendered": false, "teamIGNBSurrendered": false, "teamId": 100, "teamPosition": "BOTTOM", "timeCCingOthers": 13, "timePlayed": 1712, "totalAllyJungleMinionsKilled": 0, "totalDamageDealt": 63693, "totalDamageDealtToChampions": 9659, "totalDamageShieldedOnTeammates": 0, "totalDamageTaken": 30664, "totalEnemyJungleMinionsKilled": 0, "totalHeal": 894, "totalHealsOnTeammates": 0, "totalMinionsKilled": 71, "totalTimeCCDealt": 179, "totalTimeSpentDead": 426, "totalUnitsHealed": 1, "tripleKills": 0, "trueDamageDealt": 0, "trueDamageDealtToChampions": 0, "trueDamageTaken": 948, "turretKills": 0, "turretTakedowns": 0, "turretsLost": 13, "unrealKills": 0, "visionClearedPings": 0, "visionScore": 15, "visionWardsBoughtInGame": 0, "wardsKilled": 0, "wardsPlaced": 9, "wasPremadeWithIGNBGameEndCauser": false, "wasPremadeWithSevereTransgressor": false, "wasSevereTransgressor": false, "win": false}, {"PlayerBehavior": {"PlayerBehavior_IsHeroInCombat": 0}, "PlayerScore0": 0, "PlayerScore1": 0, "PlayerScore10": 0, "PlayerScore11": 0, "PlayerScore2": 0, "PlayerScore3": 0, "PlayerScore4": 0, "PlayerScore5": 0, "PlayerScore6": 0, "PlayerScore7": 0, "PlayerScore8": 0, "PlayerScore9": 0, "allInPings": 0, "assistMePings": 0, "assists": 5, "baronKills": 0, "basicPings": 0, "causedGameEndFromIGNBSurrender": false, "challenges": {"12AssistStreakCount": 0, "HealFromMapSources": 0, "InfernalScalePickup": 0, "SWARM_DefeatAatrox": 0, "SWARM_DefeatBriar": 0, "SWARM_DefeatMiniBosses": 0, "SWARM_EvolveWeapon": 0, "SWARM_Have3Passives": 0, "SWARM_KillEnemy": 0, "SWARM_PickupGold": 0, "SWARM_ReachLevel50": 0, "SWARM_Survive15Min": 0, "SWARM_WinWith5EvolvedWeapons": 0, "abilityUses": 264, "acesBefore15Minutes": 0, "alliedJungleMonsterKills": 0, "baronTakedowns": 0, "blastConeOppositeOpponentCount": 0, "bountyGold": 296.0743103027344, "buffsStolen": 0, "completeSupportQuestInTime": 0, "controlWardsPlaced": 0, "damagePerMinute": 498.9130399256822, "damageTakenOnTeamPercentage": 0.16349035971175815, "dancedWithRiftHerald": 0, "deathsByEnemyChamps": 15, "dodgeSkillShotsSmallWindow": 0, "doubleAces": 0, "dragonTakedowns": 0, "earlyLaningPhaseGoldExpAdvantage": 0, "effectiveHealAndShielding": 1784.9525146484375, "elderDragonKillsWithOpposingSoul": 0, "elderDragonMultikills": 0, "enemyChampionImmobilizations": 23, "enemyJungleMonsterKills": 0, "epicMonsterKillsNearEnemyJungler": 0, "epicMonsterKillsWithin30SecondsOfSpawn": 0, "epicMonsterSteals": 0, "epicMonsterStolenWithoutSmite": 0, "firstTurretKilled": 0, "fistBumpParticipation": 0, "flawlessAces": 0, "fullTeamTakedown": 0, "gameLength": 1712.120998711, "getTakedownsInAllLanesEarlyJungleAsLaner": 0, "goldPerMinute": 321.2751288871369, "hadOpenNexus": 0, "immobilizeAndKillWithAlly": 3, "initialBuffCount": 0, "initialCrabCount": 0, "jungleCsBefore10Minutes": 0, "junglerTakedownsNearDamagedEpicMonster": 0, "kTurretsDestroyedBeforePlatesFall": 0, "kda": 0.5333333333333333, "killAfterHiddenWithAlly": 0, "killParticipation": 0.4444444444444444, "killedChampTookFullTeamDamageSurvived": 0, "killingSprees": 0, "killsNearEnemyTurret": 0, "killsOnOtherLanesEarlyJungleAsLaner": 0, "killsOnRecentlyHealedByAramPack": 0, "killsUnderOwnTurret": 3, "killsWithHelpFromEpicMonster": 0, "knockEnemyIntoTeamAndKill": 0, "landSkillShotsEarlyGame": 4, "laneMinionsFirst10Minutes": 13, "laningPhaseGoldExpAdvantage": 0, "legendaryCount": 0, "legendaryItemUsed": [3871, 6655, 4646], "lostAnInhibitor": 0, "maxCsAdvantageOnLaneOpponent": 43, "maxKillDeficit": 0, "maxLevelLeadLaneOpponent": 2, "mejaisFullStackInTime": 0, "moreEnemyJungleThanOpponent": 0, "multiKillOneSpell": 0, "multiTurretRiftHeraldCount": 0, "multikills": 1, "multikillsAfterAggressiveFlash": 0, "outerTurretExecutesBefore10Minutes": 0, "outnumberedKills": 2, "outnumberedNexusKill": 0, "perfectDragonSoulsTaken": 0, "perfectGame": 0, "pickKillWithAlly": 4, "playedChampSelectPosition": 1, "poroExplosions": 0, "quickCleanse": 0, "quickFirstTurret": 0, "quickSoloKills": 0, "riftHeraldTakedowns": 0, "saveAllyFromDeath": 0, "scuttleCrabKills": 0, "shortestTimeToAceFromFirstTakedown": 32.695198334, "skillshotsDodged": 22, "skillshotsHit": 35, "snowballsHit": 0, "soloBaronKills": 0, "soloKills": 2, "stealthWardsPlaced": 17, "survivedSingleDigitHpCount": 0, "survivedThreeImmobilizesInFight": 2, "takedownOnFirstTurret": 0, "takedowns": 8, "takedownsAfterGainingLevelAdvantage": 0, "takedownsBeforeJungleMinionSpawn": 0, "takedownsFirstXMinutes": 0, "takedownsInAlcove": 0, "takedownsInEnemyFountain": 0, "teamBaronKills": 0, "teamDamagePercentage": 0.16098764391608858, "teamElderDragonKills": 0, "teamRiftHeraldKills": 1, "tookLargeDamageSurvived": 0, "turretPlatesTaken": 0, "turretTakedowns": 0, "turretsTakenWithRiftHerald": 0, "twentyMinionsIn3SecondsCount": 0, "twoWardsOneSweeperCount": 0, "unseenRecalls": 0, "visionScoreAdvantageLaneOpponent": -0.15646010637283325, "visionScorePerMinute": 1.2833374542806681, "voidMonsterKill": 0, "wardTakedowns": 2, "wardTakedownsBefore20M": 1, "wardsGuarded": 0}, "champExperience": 13667, "champLevel": 15, "championId": 99, "championName": "Lux", "championTransform": 0, "commandPings": 3, "consumablesPurchased": 3, "damageDealtToBuildings": 0, "damageDealtToEpicMonsters": 220, "damageDealtToObjectives": 220, "damageDealtToTurrets": 0, "damageSelfMitigated": 13592, "dangerPings": 0, "deaths": 15, "detectorWardsPlaced": 0, "doubleKills": 1, "dragonKills": 0, "eligibleForProgression": true, "enemyMissingPings": 5, "enemyVisionPings": 0, "firstBloodAssist": false, "firstBloodKill": false, "firstTowerAssist": false, "firstTowerKill": false, "gameEndedInEarlySurrender": false, "gameEndedInIGNBSurrender": false, "gameEndedInSurrender": false, "getBackPings": 0, "goldEarned": 9167, "goldSpent": 8825, "holdPings": 0, "individualPosition": "UTILITY", "inhibitorKills": 0, "inhibitorTakedowns": 0, "inhibitorsLost": 4, "item0": 3871, "item1": 6655, "item2": 3020, "item3": 4646, "item4": 1058, "item5": 1052, "item6": 3364, "itemsPurchased": 21, "killingSprees": 1, "kills": 3, "lane": "BOTTOM", "largestCriticalStrike": 0, "largestKillingSpree": 2, "largestMultiKill": 2, "longestTimeSpentLiving": 179, "magicDamageDealt": 77235, "magicDamageDealtToChampions": 12852, "magicDamageTaken": 11758, "missions": {"playerScore0": 0, "playerScore1": 0, "playerScore2": 0, "playerScore3": 0, "playerScore4": 0, "playerScore5": 0, "playerScore6": 0, "playerScore7": 0, "playerScore8": 0, "playerScore9": 0, "playerScore10": 0, "playerScore11": 0}, "needVisionPings": 0, "neutralMinionsKilled": 0, "nexusKills": 0, "nexusLost": 1, "nexusTakedowns": 0, "objectivesStolen": 0, "objectivesStolenAssists": 0, "onMyWayPings": 0, "participantId": 5, "pentaKills": 0, "perks": {"statPerks": {"defense": 5001, "flex": 5008, "offense": 5008}, "styles": [{"description": "primaryStyle", "selections": [{"perk": 8229, "var1": 1216, "var2": 0, "var3": 0}, {"perk": 8226, "var1": 250, "var2": 713, "var3": 0}, {"perk": 8210, "var1": 12, "var2": 0, "var3": 0}, {"perk": 8237, "var1": 360, "var2": 0, "var3": 0}], "style": 8200}, {"description": "subStyle", "selections": [{"perk": 8106, "var1": 5, "var2": 31, "var3": 0}, {"perk": 8126, "var1": 537, "var2": 0, "var3": 0}], "style": 8100}]}, "physicalDamageDealt": 5308, "physicalDamageDealtToChampions": 860, "physicalDamageTaken": 12581, "placement": 0, "playerAugment1": 0, "playerAugment2": 0, "playerAugment3": 0, "playerAugment4": 0, "playerAugment5": 0, "playerAugment6": 0, "playerSubteamId": 0, "positionAssignedByMatchmaking": "UTILITY", "profileIcon": 7064, "pushPings": 1, "puuid": "WEvsU8k6rpVdGe-t-cb37_3_u3KjZPY6W_yLyavmW3aTQhb7sykqr-36LBiOZcJ06yihJwIw2n5p8g", "quadraKills": 0, "retreatPings": 6, "riotIdGameName": "Ziur", "riotIdTagline": "EUW", "role": "DUO", "roleBoundItem": 2055, "selectedRolePreferences": "UTILITY.PRIMARY.UTILITY.TOP", "sightWardsBoughtInGame": 0, "spell1Casts": 60, "spell2Casts": 50, "spell3Casts": 145, "spell4Casts": 9, "subteamPlacement": 0, "summoner1Casts": 5, "summoner1Id": 7, "summoner2Casts": 4, "summoner2Id": 4, "summonerId": "TOxMv_6y5mbO7EzuLaVLvc6m9PnEJTAvrDyJbXwl3h9TFtU", "summonerLevel": 305, "summonerName": "", "teamEarlySurrendered": false, "teamIGNBSurrendered": false, "teamId": 100, "teamPosition": "UTILITY", "timeCCingOthers": 53, "timePlayed": 1712, "totalAllyJungleMinionsKilled": 0, "totalDamageDealt": 84122, "totalDamageDealtToChampions": 14236, "totalDamageShieldedOnTeammates": 1279, "totalDamageTaken": 24916, "totalEnemyJungleMinionsKilled": 0, "totalHeal": 1470, "totalHealsOnTeammates": 505, "totalMinionsKilled": 90, "totalTimeCCDealt": 346, "totalTimeSpentDead": 297, "totalUnitsHealed": 2, "tripleKills": 0, "trueDamageDealt": 1578, "trueDamageDealtToChampions": 523, "trueDamageTaken": 576, "turretKills": 0, "turretTakedowns": 0, "turretsLost": 13, "unrealKills": 0, "visionClearedPings": 0, "visionScore": 36, "visionWardsBoughtInGame": 2, "wardsKilled": 2, "wardsPlaced": 16, "wasPremadeWithIGNBGameEndCauser": false, "wasPremadeWithSevereTransgressor": false, "wasSevereTransgressor": false, "win": false}, {"PlayerBehavior": {"PlayerBehavior_IsHeroInCombat": 0}, "PlayerScore0": 0, "PlayerScore1": 0, "PlayerScore10": 0, "PlayerScore11": 0, "PlayerScore2": 0, "PlayerScore3": 0, "PlayerScore4": 0, "PlayerScore5": 0, "PlayerScore6": 0, "PlayerScore7": 0, "PlayerScore8": 0, "PlayerScore9": 0, "allInPings": 0, "assistMePings": 0, "assists": 14, "baronKills": 0, "basicPings": 0, "causedGameEndFromIGNBSurrender": false, "challenges": {"12AssistStreakCount": 0, "HealFromMapSources": 607.203483581543, "InfernalScalePickup": 0, "SWARM_DefeatAatrox": 0, "SWARM_DefeatBriar": 0, "SWARM_DefeatMiniBosses": 0, "SWARM_EvolveWeapon": 0, "SWARM_Have3Passives": 0, "SWARM_KillEnemy": 0, "SWARM_PickupGold": 0, "SWARM_ReachLevel50": 0, "SWARM_Survive15Min": 0, "SWARM_WinWith5EvolvedWeapons": 0, "abilityUses": 234, "acesBefore15Minutes": 0, "alliedJungleMonsterKills": 0, "baronBuffGoldAdvantageOverThreshold": 1, "baronTakedowns": 0, "blastConeOppositeOpponentCount": 0, "bountyGold": 0, "buffsStolen": 0, "completeSupportQuestInTime": 0, "controlWardsPlaced": 0, "damagePerMinute": 1076.3273949460265, "damageTakenOnTeamPercentage": 0.1973758416690167, "dancedWithRiftHerald": 0, "deathsByEnemyChamps": 4, "dodgeSkillShotsSmallWindow": 8, "doubleAces": 0, "dragonTakedowns": 0, "earliestBaron": 1664.150530051, "earlyLaningPhaseGoldExpAdvantage": 0, "effectiveHealAndShielding": 0, "elderDragonKillsWithOpposingSoul": 0, "elderDragonMultikills": 0, "enemyChampionImmobilizations": 13, "enemyJungleMonsterKills": 0, "epicMonsterKillsNearEnemyJungler": 0, "epicMonsterKillsWithin30SecondsOfSpawn": 0, "epicMonsterSteals": 0, "epicMonsterStolenWithoutSmite": 0, "fastestLegendary": 1182.1912849080002, "firstTurretKilled": 1, "firstTurretKilledTime": 804.476398012, "fistBumpParticipation": 0, "flawlessAces": 2, "fullTeamTakedown": 1, "gameLength": 1712.120998711, "getTakedownsInAllLanesEarlyJungleAsLaner": 0, "goldPerMinute": 488.1605119676056, "hadOpenNexus": 0, "immobilizeAndKillWithAlly": 8, "initialBuffCount": 0, "initialCrabCount": 0, "jungleCsBefore10Minutes": 0, "junglerTakedownsNearDamagedEpicMonster": 0, "kTurretsDestroyedBeforePlatesFall": 0, "kda": 6.5, "killAfterHiddenWithAlly": 5, "killParticipation": 0.3939393939393939, "killedChampTookFullTeamDamageSurvived": 0, "killingSprees": 1, "killsNearEnemyTurret": 5, "killsOnOtherLanesEarlyJungleAsLaner": 0, "killsOnRecentlyHealedByAramPack": 0, "killsUnderOwnTurret": 4, "killsWithHelpFromEpicMonster": 0, "knockEnemyIntoTeamAndKill": 0, "landSkillShotsEarlyGame": 0, "laneMinionsFirst10Minutes": 50, "laningPhaseGoldExpAdvantage": 0, "legendaryCount": 1, "legendaryItemUsed": [3075, 3068, 3110, 6665], "lostAnInhibitor": 0, "maxCsAdvantageOnLaneOpponent": 37, "maxKillDeficit": 0, "maxLevelLeadLaneOpponent": 4, "mejaisFullStackInTime": 0, "moreEnemyJungleThanOpponent": 0, "multiKillOneSpell": 0, "multiTurretRiftHeraldCount": 0, "multikills": 1, "multikillsAfterAggressiveFlash": 0, "outerTurretExecutesBefore10Minutes": 0, "outnumberedKills": 3, "outnumberedNexusKill": 0, "perfectDragonSoulsTaken": 1, "perfectGame": 0, "pickKillWithAlly": 16, "playedChampSelectPosition": 1, "poroExplosions": 0, "quickCleanse": 0, "quickFirstTurret": 0, "quickSoloKills": 0, "riftHeraldTakedowns": 0, "saveAllyFromDeath": 0, "scuttleCrabKills": 0, "shortestTimeToAceFromFirstTakedown": 4.284433283999988, "skillshotsDodged": 63, "skillshotsHit": 0, "snowballsHit": 0, "soloBaronKills": 0, "soloKills": 3, "soloTurretsLategame": 1, "stealthWardsPlaced": 9, "survivedSingleDigitHpCount": 0, "survivedThreeImmobilizesInFight": 4, "takedownOnFirstTurret": 0, "takedowns": 26, "takedownsAfterGainingLevelAdvantage": 0, "takedownsBeforeJungleMinionSpawn": 0, "takedownsFirstXMinutes": 4, "takedownsInAlcove": 0, "takedownsInEnemyFountain": 0, "teamBaronKills": 1, "teamDamagePercentage": 0.23253830441109907, "teamElderDragonKills": 0, "teamRiftHeraldKills": 0, "tookLargeDamageSurvived": 0, "turretPlatesTaken": 20, "turretTakedowns": 6, "turretsTakenWithRiftHerald": 0, "twentyMinionsIn3SecondsCount": 0, "twoWardsOneSweeperCount": 0, "unseenRecalls": 0, "visionScoreAdvantageLaneOpponent": -0.2705914378166199, "visionScorePerMinute": 0.6693414195717712, "voidMonsterKill": 0, "wardTakedowns": 0, "wardTakedownsBefore20M": 0, "wardsGuarded": 0}, "champExperience": 21079, "champLevel": 19, "championId": 54, "championName": "Malphite", "championTransform": 0, "commandPings": 0, "consumablesPurchased": 1, "damageDealtToBuildings": 10628, "damageDealtToEpicMonsters": 0, "damageDealtToObjectives": 10628, "damageDealtToTurrets": 10628, "damageSelfMitigated": 66224, "dangerPings": 0, "deaths": 4, "detectorWardsPlaced": 0, "doubleKills": 1, "dragonKills": 0, "eligibleForProgression": true, "enemyMissingPings": 2, "enemyVisionPings": 0, "firstBloodAssist": false, "firstBloodKill": false, "firstTowerAssist": false, "firstTowerKill": false, "gameEndedInEarlySurrender": false, "gameEndedInIGNBSurrender": false, "gameEndedInSurrender": false, "getBackPings": 0, "goldEarned": 13929, "goldSpent": 12850, "holdPings": 0, "individualPosition": "TOP", "inhibitorKills": 1, "inhibitorTakedowns": 3, "inhibitorsLost": 0, "item0": 1029, "item1": 3075, "item2": 3047, "item3": 3068, "item4": 3110, "item5": 6665, "item6": 3340, "itemsPurchased": 20, "killingSprees": 1, "kills": 12, "lane": "TOP", "largestCriticalStrike": 0, "largestKillingSpree": 10, "largestMultiKill": 2, "longestTimeSpentLiving": 942, "magicDamageDealt": 90631, "magicDamageDealtToChampions": 20642, "magicDamageTaken": 12836, "missions": {"playerScore0": 0, "playerScore1": 0, "playerScore2": 0, "playerScore3": 0, "playerScore4": 0, "playerScore5": 0, "playerScore6": 0, "playerScore7": 0, "playerScore8": 0, "playerScore9": 0, "playerScore10": 0, "playerScore11": 0}, "needVisionPings": 0, "neutralMinionsKilled": 0, "nexusKills": 1, "nexusLost": 0, "nexusTakedowns": 1, "objectivesStolen": 0, "objectivesStolenAssists": 0, "onMyWayPings": 4, "participantId": 6, "pentaKills": 0, "perks": {"statPerks": {"defense": 5001, "flex": 5001, "offense": 5005}, "styles": [{"description": "primaryStyle", "selections": [{"perk": 8437, "var1": 1765, "var2": 1081, "var3": 0}, {"perk": 8401, "var1": 1119, "var2": 0, "var3": 0}, {"perk": 8429, "var1": 57, "var2": 29, "var3": 12}, {"perk": 8451, "var1": 278, "var2": 0, "var3": 0}], "style": 8400}, {"description": "subStyle", "selections": [{"perk": 8226, "var1": 250, "var2": 520, "var3": 0}, {"perk": 8210, "var1": 43, "var2": 0, "var3": 0}], "style": 8200}]}, "physicalDamageDealt": 45160, "physicalDamageDealtToChampions": 9668, "physicalDamageTaken": 10749, "placement": 0, "playerAugment1": 0, "playerAugment2": 0, "playerAugment3": 0, "playerAugment4": 0, "playerAugment5": 0, "playerAugment6": 0, "playerSubteamId": 0, "positionAssignedByMatchmaking": "TOP", "profileIcon": 4026, "pushPings": 0, "puuid": "ZqH51cYbFoKHytcC04AW4QQEHKUQn3yPk-zB7lUPYKLuW0lwwRqBoJpi0cOrh7wBniWVSf_LrzvcUQ", "quadraKills": 0, "retreatPings": 0, "riotIdGameName": "Jean Luc Godard", "riotIdTagline": "GOAT", "role": "SOLO", "roleBoundItem": 1221, "selectedRolePreferences": "TOP.FILL_PRIMARY.FILL.UNSELECTED.FILL", "sightWardsBoughtInGame": 0, "spell1Casts": 64, "spell2Casts": 70, "spell3Casts": 89, "spell4Casts": 11, "subteamPlacement": 0, "summoner1Casts": 3, "summoner1Id": 4, "summoner2Casts": 3, "summoner2Id": 12, "summonerId": "5vDCn81rpiSAGBeGVvakB-EH5RTdtLgx3ADVwXM7P2WAAZc", "summonerLevel": 348, "summonerName": "", "teamEarlySurrendered": false, "teamIGNBSurrendered": false, "teamId": 200, "teamPosition": "TOP", "timeCCingOthers": 33, "timePlayed": 1712, "totalAllyJungleMinionsKilled": 0, "totalDamageDealt": 139007, "totalDamageDealtToChampions": 30713, "totalDamageShieldedOnTeammates": 0, "totalDamageTaken": 27789, "totalEnemyJungleMinionsKilled": 0, "totalHeal": 7863, "totalHealsOnTeammates": 0, "totalMinionsKilled": 183, "totalTimeCCDealt": 764, "totalTimeSpentDead": 153, "totalUnitsHealed": 1, "tripleKills": 0, "trueDamageDealt": 3215, "trueDamageDealtToChampions": 402, "trueDamageTaken": 4203, "turretKills": 3, "turretTakedowns": 6, "turretsLost": 1, "unrealKills": 0, "visionClearedPings": 0, "visionScore": 19, "visionWardsBoughtInGame": 0, "wardsKilled": 0, "wardsPlaced": 9, "wasPremadeWithIGNBGameEndCauser": false, "wasPremadeWithSevereTransgressor": false, "wasSevereTransgressor": false, "win": true}, {"PlayerBehavior": {"PlayerBehavior_IsHeroInCombat": 0}, "PlayerScore0": 0, "PlayerScore1": 0, "PlayerScore10": 0, "PlayerScore11": 0, "PlayerScore2": 0, "PlayerScore3": 0, "PlayerScore4": 0, "PlayerScore5": 0, "PlayerScore6": 0, "PlayerScore7": 0, "PlayerScore8": 0, "PlayerScore9": 0, "allInPings": 0, "assistMePings": 1, "assists": 15, "baronKills": 0, "basicPings": 0, "causedGameEndFromIGNBSurrender": false, "challenges": {"12AssistStreakCount": 0, "HealFromMapSources": 748, "InfernalScalePickup": 0, "SWARM_DefeatAatrox": 0, "SWARM_DefeatBriar": 0, "SWARM_DefeatMiniBosses": 0, "SWARM_EvolveWeapon": 0, "SWARM_Have3Passives": 0, "SWARM_KillEnemy": 0, "SWARM_PickupGold": 0, "SWARM_ReachLevel50": 0, "SWARM_Survive15Min": 0, "SWARM_WinWith5EvolvedWeapons": 0, "abilityUses": 355, "acesBefore15Minutes": 0, "alliedJungleMonsterKills": 71, "baronBuffGoldAdvantageOverThreshold": 1, "baronTakedowns": 1, "blastConeOppositeOpponentCount": 0, "bountyGold": 0, "buffsStolen": 3, "completeSupportQuestInTime": 0, "controlWardTimeCoverageInRiverOrEnemyHalf": 0.6771004129590037, "controlWardsPlaced": 3, "damagePerMinute": 268.5702334556448, "damageTakenOnTeamPercentage": 0.1962007292491517, "dancedWithRiftHerald": 0, "deathsByEnemyChamps": 5, "dodgeSkillShotsSmallWindow": 1, "doubleAces": 0, "dragonTakedowns": 3, "earliestBaron": 1664.150530051, "earliestDragonTakedown": 374.94869287200004, "earlyLaningPhaseGoldExpAdvantage": 0, "effectiveHealAndShielding": 811.6198120117188, "elderDragonKillsWithOpposingSoul": 0, "elderDragonMultikills": 0, "enemyChampionImmobilizations": 11, "enemyJungleMonsterKills": 15, "epicMonsterKillsNearEnemyJungler": 2, "epicMonsterKillsWithin30SecondsOfSpawn": 0, "epicMonsterSteals": 0, "epicMonsterStolenWithoutSmite": 0, "firstTurretKilled": 1, "firstTurretKilledTime": 804.476398012, "fistBumpParticipation": 0, "flawlessAces": 2, "fullTeamTakedown": 1, "gameLength": 1712.120998711, "goldPerMinute": 385.82232927233235, "hadOpenNexus": 0, "immobilizeAndKillWithAlly": 3, "initialBuffCount": 3, "initialCrabCount": 2, "jungleCsBefore10Minutes": 64.00000008940697, "junglerKillsEarlyJungle": 0, "junglerTakedownsNearDamagedEpicMonster": 0, "kTurretsDestroyedBeforePlatesFall": 0, "kda": 3.4, "killAfterHiddenWithAlly": 3, "killParticipation": 0.25757575757575757, "killedChampTookFullTeamDamageSurvived": 0, "killingSprees": 0, "killsNearEnemyTurret": 0, "killsOnLanersEarlyJungleAsJungler": 0, "killsOnRecentlyHealedByAramPack": 0, "killsUnderOwnTurret": 0, "killsWithHelpFromEpicMonster": 0, "knockEnemyIntoTeamAndKill": 3, "landSkillShotsEarlyGame": 1, "laneMinionsFirst10Minutes": 0, "laningPhaseGoldExpAdvantage": 0, "legendaryCount": 0, "legendaryItemUsed": [3074, 3156], "lostAnInhibitor": 0, "maxCsAdvantageOnLaneOpponent": 34.00000008940697, "maxKillDeficit": 0, "maxLevelLeadLaneOpponent": 2, "mejaisFullStackInTime": 0, "moreEnemyJungleThanOpponent": -41.00000008940697, "multiKillOneSpell": 0, "multiTurretRiftHeraldCount": 0, "multikills": 0, "multikillsAfterAggressiveFlash": 0, "outerTurretExecutesBefore10Minutes": 0, "outnumberedKills": 0, "outnumberedNexusKill": 0, "perfectDragonSoulsTaken": 1, "perfectGame": 0, "pickKillWithAlly": 12, "playedChampSelectPosition": 1, "poroExplosions": 0, "quickCleanse": 0, "quickFirstTurret": 0, "quickSoloKills": 0, "riftHeraldTakedowns": 0, "saveAllyFromDeath": 0, "scuttleCrabKills": 4, "skillshotsDodged": 13, "skillshotsHit": 14, "snowballsHit": 0, "soloBaronKills": 0, "soloKills": 0, "stealthWardsPlaced": 8, "survivedSingleDigitHpCount": 0, "survivedThreeImmobilizesInFight": 0, "takedownOnFirstTurret": 0, "takedowns": 17, "takedownsAfterGainingLevelAdvantage": 0, "takedownsBeforeJungleMinionSpawn": 0, "takedownsFirstXMinutes": 6, "takedownsInAlcove": 0, "takedownsInEnemyFountain": 0, "teamBaronKills": 1, "teamDamagePercentage": 0.058024042680991525, "teamElderDragonKills": 0, "teamRiftHeraldKills": 0, "tookLargeDamageSurvived": 0, "turretPlatesTaken": 0, "turretTakedowns": 2, "turretsTakenWithRiftHerald": 0, "twentyMinionsIn3SecondsCount": 0, "twoWardsOneSweeperCount": 0, "unseenRecalls": 0, "visionScoreAdvantageLaneOpponent": 0.3028057813644409, "visionScorePerMinute": 1.0828936469959938, "voidMonsterKill": 2, "wardTakedowns": 4, "wardTakedownsBefore20M": 1, "wardsGuarded": 0}, "champExperience": 14732, "champLevel": 16, "championId": 64, "championName": "LeeSin", "championTransform": 0, "commandPings": 0, "consumablesPurchased": 4, "damageDealtToBuildings": 447, "damageDealtToEpicMonsters": 22383, "damageDealtToObjectives": 22830, "damageDealtToTurrets": 447, "damageSelfMitigated": 20268, "dangerPings": 0, "deaths": 5, "detectorWardsPlaced": 4, "doubleKills": 0, "dragonKills": 3, "eligibleForProgression": true, "enemyMissingPings": 0, "enemyVisionPings": 0, "firstBloodAssist": false, "firstBloodKill": false, "firstTowerAssist": false, "firstTowerKill": false, "gameEndedInEarlySurrender": false, "gameEndedInIGNBSurrender": false, "gameEndedInSurrender": false, "getBackPings": 0, "goldEarned": 11009, "goldSpent": 9250, "holdPings": 0, "individualPosition": "JUNGLE", "inhibitorKills": 0, "inhibitorTakedowns": 1, "inhibitorsLost": 0, "item0": 3074, "item1": 3156, "item2": 3067, "item3": 3047, "item4": 1028, "item5": 0, "item6": 3340, "itemsPurchased": 22, "killingSprees": 0, "kills": 2, "lane": "JUNGLE", "largestCriticalStrike": 0, "largestKillingSpree": 0, "largestMultiKill": 1, "longestTimeSpentLiving": 502, "magicDamageDealt": 33502, "magicDamageDealtToChampions": 1541, "magicDamageTaken": 8158, "missions": {"playerScore0": 0, "playerScore1": 0, "playerScore2": 0, "playerScore3": 0, "playerScore4": 0, "playerScore5": 0, "playerScore6": 0, "playerScore7": 0, "playerScore8": 0, "playerScore9": 0, "playerScore10": 0, "playerScore11": 0}, "needVisionPings": 0, "neutralMinionsKilled": 155, "nexusKills": 0, "nexusLost": 0, "nexusTakedowns": 1, "objectivesStolen": 0, "objectivesStolenAssists": 0, "onMyWayPings": 8, "participantId": 7, "pentaKills": 0, "perks": {"statPerks": {"defense": 5001, "flex": 5008, "offense": 5005}, "styles": [{"description": "primaryStyle", "selections": [{"perk": 8010, "var1": 1, "var2": 0, "var3": 0}, {"perk": 9111, "var1": 956, "var2": 340, "var3": 0}, {"perk": 9104, "var1": 12, "var2": 0, "var3": 0}, {"perk": 8014, "var1": 298, "var2": 0, "var3": 0}], "style": 8000}, {"description": "subStyle", "selections": [{"perk": 8347, "var1": 0, "var2": 0, "var3": 0}, {"perk": 8304, "var1": 10, "var2": 3, "var3": 0}], "style": 8300}]}, "physicalDamageDealt": 93497, "physicalDamageDealtToChampions": 5845, "physicalDamageTaken": 16390, "placement": 0, "playerAugment1": 0, "playerAugment2": 0, "playerAugment3": 0, "playerAugment4": 0, "playerAugment5": 0, "playerAugment6": 0, "playerSubteamId": 0, "positionAssignedByMatchmaking": "JUNGLE", "profileIcon": 3543, "pushPings": 0, "puuid": "dfv_8GpGQuO4scvh-z1i0cyI-zRt54kYqBut64baWmF_Ltq2hZIV3X-0cm6Lz-OgySvSGRdXNfKzlQ", "quadraKills": 0, "retreatPings": 0, "riotIdGameName": "lebosswlh", "riotIdTagline": "EUW", "role": "NONE", "roleBoundItem": 1209, "selectedRolePreferences": "JUNGLE.FILL_PRIMARY.FILL.UNSELECTED.FILL", "sightWardsBoughtInGame": 0, "spell1Casts": 160, "spell2Casts": 48, "spell3Casts": 140, "spell4Casts": 7, "subteamPlacement": 0, "summoner1Casts": 17, "summoner1Id": 11, "summoner2Casts": 3, "summoner2Id": 4, "summonerId": "pFh36bd7V4ZgxXCckm8uhyVkP6XvmL8Di6vj87awNujOLqXQbVcmiURF9A", "summonerLevel": 140, "summonerName": "", "teamEarlySurrendered": false, "teamIGNBSurrendered": false, "teamId": 200, "teamPosition": "JUNGLE", "timeCCingOthers": 9, "timePlayed": 1712, "totalAllyJungleMinionsKilled": 102, "totalDamageDealt": 220906, "totalDamageDealtToChampions": 7663, "totalDamageShieldedOnTeammates": 811, "totalDamageTaken": 27624, "totalEnemyJungleMinionsKilled": 20, "totalHeal": 14228, "totalHealsOnTeammates": 0, "totalMinionsKilled": 22, "totalTimeCCDealt": 362, "totalTimeSpentDead": 158, "totalUnitsHealed": 1, "tripleKills": 0, "trueDamageDealt": 93907, "trueDamageDealtToChampions": 276, "trueDamageTaken": 3075, "turretKills": 0, "turretTakedowns": 2, "turretsLost": 1, "unrealKills": 0, "visionClearedPings": 0, "visionScore": 30, "visionWardsBoughtInGame": 4, "wardsKilled": 4, "wardsPlaced": 12, "wasPremadeWithIGNBGameEndCauser": false, "wasPremadeWithSevereTransgressor": false, "wasSevereTransgressor": false, "win": true}, {"PlayerBehavior": {"PlayerBehavior_IsHeroInCombat": 0}, "PlayerScore0": 0, "PlayerScore1": 0, "PlayerScore10": 0, "PlayerScore11": 0, "PlayerScore2": 0, "PlayerScore3": 0, "PlayerScore4": 0, "PlayerScore5": 0, "PlayerScore6": 0, "PlayerScore7": 0, "PlayerScore8": 0, "PlayerScore9": 0, "allInPings": 0, "assistMePings": 0, "assists": 9, "baronKills": 0, "basicPings": 0, "causedGameEndFromIGNBSurrender": false, "challenges": {"12AssistStreakCount": 0, "HealFromMapSources": 160, "InfernalScalePickup": 0, "SWARM_DefeatAatrox": 0, "SWARM_DefeatBriar": 0, "SWARM_DefeatMiniBosses": 0, "SWARM_EvolveWeapon": 0, "SWARM_Have3Passives": 0, "SWARM_KillEnemy": 0, "SWARM_PickupGold": 0, "SWARM_ReachLevel50": 0, "SWARM_Survive15Min": 0, "SWARM_WinWith5EvolvedWeapons": 0, "abilityUses": 295, "acesBefore15Minutes": 0, "alliedJungleMonsterKills": 0, "baronBuffGoldAdvantageOverThreshold": 1, "baronTakedowns": 1, "blastConeOppositeOpponentCount": 0, "bountyGold": 0, "buffsStolen": 0, "completeSupportQuestInTime": 0, "controlWardsPlaced": 0, "damagePerMinute": 765.1221840037839, "damageTakenOnTeamPercentage": 0.13228517576212964, "dancedWithRiftHerald": 0, "deathsByEnemyChamps": 2, "dodgeSkillShotsSmallWindow": 6, "doubleAces": 0, "dragonTakedowns": 0, "earliestBaron": 1664.150530051, "earlyLaningPhaseGoldExpAdvantage": 1, "effectiveHealAndShielding": 0, "elderDragonKillsWithOpposingSoul": 0, "elderDragonMultikills": 0, "enemyChampionImmobilizations": 0, "enemyJungleMonsterKills": 0, "epicMonsterKillsNearEnemyJungler": 0, "epicMonsterKillsWithin30SecondsOfSpawn": 0, "epicMonsterSteals": 0, "epicMonsterStolenWithoutSmite": 0, "fastestLegendary": 1367.909785237, "firstTurretKilled": 1, "firstTurretKilledTime": 804.476398012, "fistBumpParticipation": 0, "flawlessAces": 2, "fullTeamTakedown": 1, "gameLength": 1712.120998711, "getTakedownsInAllLanesEarlyJungleAsLaner": 0, "goldPerMinute": 444.5782958742761, "hadOpenNexus": 0, "immobilizeAndKillWithAlly": 0, "initialBuffCount": 0, "initialCrabCount": 0, "jungleCsBefore10Minutes": 0, "junglerTakedownsNearDamagedEpicMonster": 0, "kTurretsDestroyedBeforePlatesFall": 0, "kda": 9.5, "killAfterHiddenWithAlly": 4, "killParticipation": 0.2878787878787879, "killedChampTookFullTeamDamageSurvived": 0, "killingSprees": 1, "killsNearEnemyTurret": 7, "killsOnOtherLanesEarlyJungleAsLaner": 0, "killsOnRecentlyHealedByAramPack": 0, "killsUnderOwnTurret": 0, "killsWithHelpFromEpicMonster": 0, "knockEnemyIntoTeamAndKill": 0, "landSkillShotsEarlyGame": 12, "laneMinionsFirst10Minutes": 78, "laningPhaseGoldExpAdvantage": 0, "legendaryCount": 1, "legendaryItemUsed": [6699, 6692, 6694], "lostAnInhibitor": 0, "maxCsAdvantageOnLaneOpponent": 10, "maxKillDeficit": 0, "maxLevelLeadLaneOpponent": 2, "mejaisFullStackInTime": 0, "moreEnemyJungleThanOpponent": 0, "multiKillOneSpell": 0, "multiTurretRiftHeraldCount": 0, "multikills": 0, "multikillsAfterAggressiveFlash": 0, "outerTurretExecutesBefore10Minutes": 0, "outnumberedKills": 3, "outnumberedNexusKill": 0, "perfectDragonSoulsTaken": 1, "perfectGame": 0, "pickKillWithAlly": 14, "playedChampSelectPosition": 1, "poroExplosions": 0, "quickCleanse": 0, "quickFirstTurret": 0, "quickSoloKills": 0, "riftHeraldTakedowns": 0, "saveAllyFromDeath": 0, "scuttleCrabKills": 0, "skillshotsDodged": 52, "skillshotsHit": 43, "snowballsHit": 0, "soloBaronKills": 0, "soloKills": 2, "stealthWardsPlaced": 10, "survivedSingleDigitHpCount": 0, "survivedThreeImmobilizesInFight": 0, "takedownOnFirstTurret": 0, "takedowns": 19, "takedownsAfterGainingLevelAdvantage": 1, "takedownsBeforeJungleMinionSpawn": 0, "takedownsFirstXMinutes": 4, "takedownsInAlcove": 0, "takedownsInEnemyFountain": 0, "teamBaronKills": 1, "teamDamagePercentage": 0.1653030631488097, "teamElderDragonKills": 0, "teamRiftHeraldKills": 0, "tookLargeDamageSurvived": 0, "turretPlatesTaken": 13, "turretTakedowns": 5, "turretsTakenWithRiftHerald": 0, "twentyMinionsIn3SecondsCount": 0, "twoWardsOneSweeperCount": 0, "unseenRecalls": 0, "visionScoreAdvantageLaneOpponent": 0.6365664005279541, "visionScorePerMinute": 0.6239435362620978, "voidMonsterKill": 1, "wardTakedowns": 0, "wardTakedownsBefore20M": 0, "wardsGuarded": 0}, "champExperience": 16070, "champLevel": 16, "championId": 238, "championName": "Zed", "championTransform": 0, "commandPings": 0, "consumablesPurchased": 1, "damageDealtToBuildings": 10574, "damageDealtToEpicMonsters": 6064, "damageDealtToObjectives": 16639, "damageDealtToTurrets": 10574, "damageSelfMitigated": 12649, "dangerPings": 0, "deaths": 2, "detectorWardsPlaced": 0, "doubleKills": 0, "dragonKills": 0, "eligibleForProgression": true, "enemyMissingPings": 3, "enemyVisionPings": 2, "firstBloodAssist": false, "firstBloodKill": false, "firstTowerAssist": false, "firstTowerKill": false, "gameEndedInEarlySurrender": false, "gameEndedInIGNBSurrender": false, "gameEndedInSurrender": false, "getBackPings": 0, "goldEarned": 12686, "goldSpent": 11650, "holdPings": 0, "individualPosition": "MIDDLE", "inhibitorKills": 2, "inhibitorTakedowns": 2, "inhibitorsLost": 0, "item0": 6694, "item1": 6699, "item2": 3171, "item3": 6692, "item4": 3134, "item5": 1036, "item6": 3340, "itemsPurchased": 20, "killingSprees": 1, "kills": 10, "lane": "MIDDLE", "largestCriticalStrike": 0, "largestKillingSpree": 8, "largestMultiKill": 1, "longestTimeSpentLiving": 1480, "magicDamageDealt": 6225, "magicDamageDealtToChampions": 861, "magicDamageTaken": 11550, "missions": {"playerScore0": 0, "playerScore1": 0, "playerScore2": 0, "playerScore3": 0, "playerScore4": 0, "playerScore5": 0, "playerScore6": 0, "playerScore7": 0, "playerScore8": 0, "playerScore9": 0, "playerScore10": 0, "playerScore11": 0}, "needVisionPings": 0, "neutralMinionsKilled": 0, "nexusKills": 0, "nexusLost": 0, "nexusTakedowns": 1, "objectivesStolen": 0, "objectivesStolenAssists": 0, "onMyWayPings": 0, "participantId": 8, "pentaKills": 0, "perks": {"statPerks": {"defense": 5001, "flex": 5008, "offense": 5008}, "styles": [{"description": "primaryStyle", "selections": [{"perk": 8112, "var1": 1360, "var2": 0, "var3": 0}, {"perk": 8143, "var1": 915, "var2": 0, "var3": 0}, {"perk": 8140, "var1": 18, "var2": 0, "var3": 0}, {"perk": 8106, "var1": 5, "var2": 31, "var3": 0}], "style": 8100}, {"description": "subStyle", "selections": [{"perk": 8014, "var1": 1034, "var2": 0, "var3": 0}, {"perk": 9111, "var1": 1153, "var2": 380, "var3": 0}], "style": 8000}]}, "physicalDamageDealt": 132355, "physicalDamageDealtToChampions": 19471, "physicalDamageTaken": 6863, "placement": 0, "playerAugment1": 0, "playerAugment2": 0, "playerAugment3": 0, "playerAugment4": 0, "playerAugment5": 0, "playerAugment6": 0, "playerSubteamId": 0, "positionAssignedByMatchmaking": "MIDDLE", "profileIcon": 7128, "pushPings": 0, "puuid": "ZGzDetUV02Pb018-5Lx34wsZE5N7eFzonCL1SR2I1r4qhsK72_l3xo9JhrhxoU-rrUbAjXQK_T6GEw", "quadraKills": 0, "retreatPings": 0, "riotIdGameName": "Roller Coaster", "riotIdTagline": "abouf", "role": "SOLO", "roleBoundItem": 1206, "selectedRolePreferences": "MIDDLE.FILL_PRIMARY.FILL.UNSELECTED.FILL", "sightWardsBoughtInGame": 0, "spell1Casts": 99, "spell2Casts": 72, "spell3Casts": 112, "spell4Casts": 12, "subteamPlacement": 0, "summoner1Casts": 6, "summoner1Id": 14, "summoner2Casts": 4, "summoner2Id": 4, "summonerId": "tV5sWLt52pYcT2GIdwOf-uOzWsB6t0ofMIc1xXbBVx19zGXSbfrl0BNOQA", "summonerLevel": 41, "summonerName": "", "teamEarlySurrendered": false, "teamIGNBSurrendered": false, "teamId": 200, "teamPosition": "MIDDLE", "timeCCingOthers": 5, "timePlayed": 1712, "totalAllyJungleMinionsKilled": 0, "totalDamageDealt": 141251, "totalDamageDealtToChampions": 21833, "totalDamageShieldedOnTeammates": 0, "totalDamageTaken": 18625, "totalEnemyJungleMinionsKilled": 0, "totalHeal": 6506, "totalHealsOnTeammates": 0, "totalMinionsKilled": 187, "totalTimeCCDealt": 94, "totalTimeSpentDead": 97, "totalUnitsHealed": 1, "tripleKills": 0, "trueDamageDealt": 2671, "trueDamageDealtToChampions": 1499, "trueDamageTaken": 211, "turretKills": 4, "turretTakedowns": 5, "turretsLost": 1, "unrealKills": 0, "visionClearedPings": 0, "visionScore": 17, "visionWardsBoughtInGame": 0, "wardsKilled": 0, "wardsPlaced": 10, "wasPremadeWithIGNBGameEndCauser": false, "wasPremadeWithSevereTransgressor": false, "wasSevereTransgressor": false, "win": true}, {"PlayerBehavior": {"PlayerBehavior_IsHeroInCombat": 0}, "PlayerScore0": 0, "PlayerScore1": 0, "PlayerScore10": 0, "PlayerScore11": 0, "PlayerScore2": 0, "PlayerScore3": 0, "PlayerScore4": 0, "PlayerScore5": 0, "PlayerScore6": 0, "PlayerScore7": 0, "PlayerScore8": 0, "PlayerScore9": 0, "allInPings": 0, "assistMePings": 2, "assists": 9, "baronKills": 1, "basicPings": 0, "causedGameEndFromIGNBSurrender": false, "challenges": {"12AssistStreakCount": 0, "HealFromMapSources": 743.9033432006836, "InfernalScalePickup": 0, "SWARM_DefeatAatrox": 0, "SWARM_DefeatBriar": 0, "SWARM_DefeatMiniBosses": 0, "SWARM_EvolveWeapon": 0, "SWARM_Have3Passives": 0, "SWARM_KillEnemy": 0, "SWARM_PickupGold": 0, "SWARM_ReachLevel50": 0, "SWARM_Survive15Min": 0, "SWARM_WinWith5EvolvedWeapons": 0, "abilityUses": 174, "acesBefore15Minutes": 0, "alliedJungleMonsterKills": 0, "baronBuffGoldAdvantageOverThreshold": 1, "baronTakedowns": 1, "blastConeOppositeOpponentCount": 0, "bountyGold": 0, "buffsStolen": 2, "completeSupportQuestInTime": 0, "controlWardsPlaced": 0, "damagePerMinute": 1694.3482504647832, "damageTakenOnTeamPercentage": 0.29397661352745535, "dancedWithRiftHerald": 0, "deathsByEnemyChamps": 3, "dodgeSkillShotsSmallWindow": 3, "doubleAces": 0, "dragonTakedowns": 2, "earliestBaron": 1664.150530051, "earliestDragonTakedown": 742.439996853, "earlyLaningPhaseGoldExpAdvantage": 1, "effectiveHealAndShielding": 407.86962890625, "elderDragonKillsWithOpposingSoul": 0, "elderDragonMultikills": 0, "enemyChampionImmobilizations": 0, "enemyJungleMonsterKills": 4, "epicMonsterKillsNearEnemyJungler": 0, "epicMonsterKillsWithin30SecondsOfSpawn": 0, "epicMonsterSteals": 0, "epicMonsterStolenWithoutSmite": 0, "fastestLegendary": 502.380446047, "firstTurretKilled": 1, "firstTurretKilledTime": 804.476398012, "fistBumpParticipation": 0, "flawlessAces": 2, "fullTeamTakedown": 1, "gameLength": 1712.120998711, "getTakedownsInAllLanesEarlyJungleAsLaner": 0, "goldPerMinute": 692.2408855111867, "hadOpenNexus": 0, "highestChampionDamage": 1, "immobilizeAndKillWithAlly": 0, "initialBuffCount": 0, "initialCrabCount": 0, "jungleCsBefore10Minutes": 0, "junglerTakedownsNearDamagedEpicMonster": 1, "kTurretsDestroyedBeforePlatesFall": 0, "kda": 14.666666666666666, "killAfterHiddenWithAlly": 9, "killParticipation": 0.6666666666666666, "killedChampTookFullTeamDamageSurvived": 0, "killingSprees": 4, "killsNearEnemyTurret": 20, "killsOnOtherLanesEarlyJungleAsLaner": 1, "killsOnRecentlyHealedByAramPack": 0, "killsUnderOwnTurret": 0, "killsWithHelpFromEpicMonster": 2, "knockEnemyIntoTeamAndKill": 0, "landSkillShotsEarlyGame": 0, "laneMinionsFirst10Minutes": 73, "laningPhaseGoldExpAdvantage": 1, "legendaryCount": 3, "legendaryItemUsed": [6672, 3153, 3302, 6665, 3748], "lostAnInhibitor": 0, "maxCsAdvantageOnLaneOpponent": 145, "maxKillDeficit": 0, "maxLevelLeadLaneOpponent": 6, "mejaisFullStackInTime": 0, "moreEnemyJungleThanOpponent": 0, "multiKillOneSpell": 0, "multiTurretRiftHeraldCount": 0, "multikills": 17, "multikillsAfterAggressiveFlash": 0, "outerTurretExecutesBefore10Minutes": 0, "outnumberedKills": 11, "outnumberedNexusKill": 0, "perfectDragonSoulsTaken": 1, "perfectGame": 0, "pickKillWithAlly": 30, "playedChampSelectPosition": 1, "poroExplosions": 0, "quickCleanse": 0, "quickFirstTurret": 0, "quickSoloKills": 0, "riftHeraldTakedowns": 0, "saveAllyFromDeath": 0, "scuttleCrabKills": 0, "shortestTimeToAceFromFirstTakedown": 4.284433283999988, "skillshotsDodged": 56, "skillshotsHit": 4, "snowballsHit": 0, "soloBaronKills": 0, "soloKills": 7, "soloTurretsLategame": 1, "stealthWardsPlaced": 9, "survivedSingleDigitHpCount": 0, "survivedThreeImmobilizesInFight": 2, "takedownOnFirstTurret": 0, "takedowns": 44, "takedownsAfterGainingLevelAdvantage": 0, "takedownsBeforeJungleMinionSpawn": 0, "takedownsFirstXMinutes": 22, "takedownsInAlcove": 2, "takedownsInEnemyFountain": 0, "teamBaronKills": 1, "teamDamagePercentage": 0.36606043021394097, "teamElderDragonKills": 0, "teamRiftHeraldKills": 0, "tookLargeDamageSurvived": 0, "turretPlatesTaken": 19, "turretTakedowns": 5, "turretsTakenWithRiftHerald": 0, "twentyMinionsIn3SecondsCount": 0, "twoWardsOneSweeperCount": 0, "unseenRecalls": 0, "visionScoreAdvantageLaneOpponent": 0.2795073986053467, "visionScorePerMinute": 0.6949129461048541, "voidMonsterKill": 1, "wardTakedowns": 1, "wardTakedownsBefore20M": 1, "wardsGuarded": 0}, "champExperience": 17166, "champLevel": 17, "championId": 55, "championName": "Katarina", "championTransform": 0, "commandPings": 2, "consumablesPurchased": 1, "damageDealtToBuildings": 10354, "damageDealtToEpicMonsters": 13221, "damageDealtToObjectives": 23575, "damageDealtToTurrets": 10354, "damageSelfMitigated": 34631, "dangerPings": 0, "deaths": 3, "detectorWardsPlaced": 0, "doubleKills": 9, "dragonKills": 1, "eligibleForProgression": true, "enemyMissingPings": 0, "enemyVisionPings": 1, "firstBloodAssist": true, "firstBloodKill": false, "firstTowerAssist": false, "firstTowerKill": false, "gameEndedInEarlySurrender": false, "gameEndedInIGNBSurrender": false, "gameEndedInSurrender": false, "getBackPings": 0, "goldEarned": 19753, "goldSpent": 17200, "holdPings": 0, "individualPosition": "BOTTOM", "inhibitorKills": 0, "inhibitorTakedowns": 2, "inhibitorsLost": 0, "item0": 1055, "item1": 3748, "item2": 3153, "item3": 3302, "item4": 6665, "item5": 6672, "item6": 3340, "itemsPurchased": 20, "killingSprees": 4, "kills": 35, "lane": "BOTTOM", "largestCriticalStrike": 0, "largestKillingSpree": 12, "largestMultiKill": 4, "longestTimeSpentLiving": 662, "magicDamageDealt": 85519, "magicDamageDealtToChampions": 18534, "magicDamageTaken": 16615, "missions": {"playerScore0": 0, "playerScore1": 0, "playerScore2": 0, "playerScore3": 0, "playerScore4": 0, "playerScore5": 0, "playerScore6": 0, "playerScore7": 0, "playerScore8": 0, "playerScore9": 0, "playerScore10": 0, "playerScore11": 0}, "needVisionPings": 0, "neutralMinionsKilled": 20, "nexusKills": 0, "nexusLost": 0, "nexusTakedowns": 1, "objectivesStolen": 0, "objectivesStolenAssists": 0, "onMyWayPings": 2, "participantId": 9, "pentaKills": 0, "perks": {"statPerks": {"defense": 5011, "flex": 5008, "offense": 5005}, "styles": [{"description": "primaryStyle", "selections": [{"perk": 8010, "var1": 1968, "var2": 0, "var3": 0}, {"perk": 9111, "var1": 2949, "var2": 880, "var3": 0}, {"perk": 9104, "var1": 6, "var2": 10, "var3": 0}, {"perk": 8014, "var1": 2881, "var2": 0, "var3": 0}], "style": 8000}, {"description": "subStyle", "selections": [{"perk": 8143, "var1": 1394, "var2": 0, "var3": 0}, {"perk": 8105, "var1": 40, "var2": 5, "var3": 0}], "style": 8100}]}, "physicalDamageDealt": 102330, "physicalDamageDealtToChampions": 28044, "physicalDamageTaken": 21565, "placement": 0, "playerAugment1": 0, "playerAugment2": 0, "playerAugment3": 0, "playerAugment4": 0, "playerAugment5": 0, "playerAugment6": 0, "playerSubteamId": 0, "positionAssignedByMatchmaking": "BOTTOM", "profileIcon": 6868, "pushPings": 0, "puuid": "fT29JLAIOS45Ni2ebQUZUannR8ndWP9lXx__YWLhGihIN_FDCk86nsPj_pFY38bLTWLEHTxfdRolmw", "quadraKills": 3, "retreatPings": 0, "riotIdGameName": "GOLGOROTH", "riotIdTagline": "noeil", "role": "CARRY", "roleBoundItem": 3008, "selectedRolePreferences": "BOTTOM.FILL_PRIMARY.FILL.UNSELECTED.FILL", "sightWardsBoughtInGame": 0, "spell1Casts": 92, "spell2Casts": 68, "spell3Casts": 0, "spell4Casts": 14, "subteamPlacement": 0, "summoner1Casts": 4, "summoner1Id": 4, "summoner2Casts": 3, "summoner2Id": 7, "summonerId": "RIUUrbMqTDBg_zEVe949zbSx5YP1Gdp3zRYXJjgOSkn74pUR5CYbrZ2m_A", "summonerLevel": 55, "summonerName": "", "teamEarlySurrendered": false, "teamIGNBSurrendered": false, "teamId": 200, "teamPosition": "BOTTOM", "timeCCingOthers": 7, "timePlayed": 1711, "totalAllyJungleMinionsKilled": 0, "totalDamageDealt": 193696, "totalDamageDealtToChampions": 48348, "totalDamageShieldedOnTeammates": 0, "totalDamageTaken": 41390, "totalEnemyJungleMinionsKilled": 10, "totalHeal": 26102, "totalHealsOnTeammates": 407, "totalMinionsKilled": 185, "totalTimeCCDealt": 89, "totalTimeSpentDead": 121, "totalUnitsHealed": 3, "tripleKills": 5, "trueDamageDealt": 5846, "trueDamageDealtToChampions": 1769, "trueDamageTaken": 3209, "turretKills": 3, "turretTakedowns": 5, "turretsLost": 1, "unrealKills": 0, "visionClearedPings": 0, "visionScore": 19, "visionWardsBoughtInGame": 0, "wardsKilled": 1, "wardsPlaced": 10, "wasPremadeWithIGNBGameEndCauser": false, "wasPremadeWithSevereTransgressor": false, "wasSevereTransgressor": false, "win": true}, {"PlayerBehavior": {"PlayerBehavior_IsHeroInCombat": 0}, "PlayerScore0": 0, "PlayerScore1": 0, "PlayerScore10": 0, "PlayerScore11": 0, "PlayerScore2": 0, "PlayerScore3": 0, "PlayerScore4": 0, "PlayerScore5": 0, "PlayerScore6": 0, "PlayerScore7": 0, "PlayerScore8": 0, "PlayerScore9": 0, "allInPings": 0, "assistMePings": 0, "assists": 31, "baronKills": 0, "basicPings": 0, "causedGameEndFromIGNBSurrender": false, "challenges": {"12AssistStreakCount": 0, "HealFromMapSources": 329.1050338745117, "InfernalScalePickup": 0, "SWARM_DefeatAatrox": 0, "SWARM_DefeatBriar": 0, "SWARM_DefeatMiniBosses": 0, "SWARM_EvolveWeapon": 0, "SWARM_Have3Passives": 0, "SWARM_KillEnemy": 0, "SWARM_PickupGold": 0, "SWARM_ReachLevel50": 0, "SWARM_Survive15Min": 0, "SWARM_WinWith5EvolvedWeapons": 0, "abilityUses": 210, "acesBefore15Minutes": 0, "alliedJungleMonsterKills": 0, "baronBuffGoldAdvantageOverThreshold": 1, "baronTakedowns": 0, "blastConeOppositeOpponentCount": 0, "bountyGold": 0, "buffsStolen": 0, "completeSupportQuestInTime": 1, "controlWardsPlaced": 0, "damagePerMinute": 824.234513689417, "damageTakenOnTeamPercentage": 0.18016163979224656, "dancedWithRiftHerald": 0, "deathsByEnemyChamps": 4, "dodgeSkillShotsSmallWindow": 5, "doubleAces": 0, "dragonTakedowns": 1, "earliestBaron": 1664.150530051, "earliestDragonTakedown": 374.94869287200004, "earlyLaningPhaseGoldExpAdvantage": 1, "effectiveHealAndShielding": 0, "elderDragonKillsWithOpposingSoul": 0, "elderDragonMultikills": 0, "enemyChampionImmobilizations": 58, "enemyJungleMonsterKills": 0, "epicMonsterKillsNearEnemyJungler": 0, "epicMonsterKillsWithin30SecondsOfSpawn": 0, "epicMonsterSteals": 0, "epicMonsterStolenWithoutSmite": 0, "fasterSupportQuestCompletion": 1, "firstTurretKilled": 1, "firstTurretKilledTime": 804.476398012, "fistBumpParticipation": 0, "flawlessAces": 2, "fullTeamTakedown": 1, "gameLength": 1712.120998711, "getTakedownsInAllLanesEarlyJungleAsLaner": 0, "goldPerMinute": 436.4928271535068, "hadOpenNexus": 0, "highestCrowdControlScore": 1, "highestWardKills": 1, "immobilizeAndKillWithAlly": 27, "initialBuffCount": 0, "initialCrabCount": 0, "jungleCsBefore10Minutes": 0, "junglerTakedownsNearDamagedEpicMonster": 0, "kTurretsDestroyedBeforePlatesFall": 1, "kda": 9.5, "killAfterHiddenWithAlly": 7, "killParticipation": 0.5757575757575758, "killedChampTookFullTeamDamageSurvived": 0, "killingSprees": 1, "killsNearEnemyTurret": 3, "killsOnOtherLanesEarlyJungleAsLaner": 0, "killsOnRecentlyHealedByAramPack": 0, "killsUnderOwnTurret": 0, "killsWithHelpFromEpicMonster": 1, "knockEnemyIntoTeamAndKill": 0, "landSkillShotsEarlyGame": 19, "laneMinionsFirst10Minutes": 9, "laningPhaseGoldExpAdvantage": 1, "legendaryCount": 0, "legendaryItemUsed": [3152, 3871, 3157, 4646], "lostAnInhibitor": 0, "maxCsAdvantageOnLaneOpponent": 0, "maxKillDeficit": 0, "maxLevelLeadLaneOpponent": 2, "mejaisFullStackInTime": 0, "moreEnemyJungleThanOpponent": 0, "multiKillOneSpell": 0, "multiTurretRiftHeraldCount": 0, "multikills": 0, "multikillsAfterAggressiveFlash": 0, "outerTurretExecutesBefore10Minutes": 0, "outnumberedKills": 1, "outnumberedNexusKill": 0, "perfectDragonSoulsTaken": 1, "perfectGame": 0, "pickKillWithAlly": 30, "playedChampSelectPosition": 1, "poroExplosions": 0, "quickCleanse": 0, "quickFirstTurret": 0, "quickSoloKills": 0, "riftHeraldTakedowns": 0, "saveAllyFromDeath": 0, "scuttleCrabKills": 0, "shortestTimeToAceFromFirstTakedown": 4.284433283999988, "skillshotsDodged": 59, "skillshotsHit": 57, "snowballsHit": 0, "soloBaronKills": 0, "soloKills": 1, "stealthWardsPlaced": 14, "survivedSingleDigitHpCount": 0, "survivedThreeImmobilizesInFight": 0, "takedownOnFirstTurret": 1, "takedowns": 38, "takedownsAfterGainingLevelAdvantage": 0, "takedownsBeforeJungleMinionSpawn": 0, "takedownsFirstXMinutes": 20, "takedownsInAlcove": 0, "takedownsInEnemyFountain": 0, "teamBaronKills": 1, "teamDamagePercentage": 0.17807415954515876, "teamElderDragonKills": 0, "teamRiftHeraldKills": 0, "tookLargeDamageSurvived": 0, "turretPlatesTaken": 17, "turretTakedowns": 5, "turretsTakenWithRiftHerald": 0, "twentyMinionsIn3SecondsCount": 0, "twoWardsOneSweeperCount": 2, "unseenRecalls": 0, "visionScoreAdvantageLaneOpponent": 0.18548035621643066, "visionScorePerMinute": 1.5213713768270836, "voidMonsterKill": 0, "wardTakedowns": 5, "wardTakedownsBefore20M": 5, "wardsGuarded": 0}, "champExperience": 13177, "champLevel": 15, "championId": 518, "championName": "Neeko", "championTransform": 0, "commandPings": 0, "consumablesPurchased": 2, "damageDealtToBuildings": 9196, "damageDealtToEpicMonsters": 618, "damageDealtToObjectives": 9814, "damageDealtToTurrets": 9196, "damageSelfMitigated": 12726, "dangerPings": 0, "deaths": 4, "detectorWardsPlaced": 0, "doubleKills": 0, "dragonKills": 0, "eligibleForProgression": true, "enemyMissingPings": 0, "enemyVisionPings": 1, "firstBloodAssist": false, "firstBloodKill": true, "firstTowerAssist": false, "firstTowerKill": true, "gameEndedInEarlySurrender": false, "gameEndedInIGNBSurrender": false, "gameEndedInSurrender": false, "getBackPings": 0, "goldEarned": 12455, "goldSpent": 10500, "holdPings": 0, "individualPosition": "UTILITY", "inhibitorKills": 0, "inhibitorTakedowns": 1, "inhibitorsLost": 0, "item0": 3152, "item1": 3157, "item2": 3871, "item3": 3158, "item4": 4646, "item5": 1052, "item6": 3364, "itemsPurchased": 24, "killingSprees": 1, "kills": 7, "lane": "BOTTOM", "largestCriticalStrike": 0, "largestKillingSpree": 5, "largestMultiKill": 1, "longestTimeSpentLiving": 1098, "magicDamageDealt": 77574, "magicDamageDealtToChampions": 21169, "magicDamageTaken": 11068, "missions": {"playerScore0": 0, "playerScore1": 0, "playerScore2": 0, "playerScore3": 0, "playerScore4": 0, "playerScore5": 0, "playerScore6": 0, "playerScore7": 0, "playerScore8": 0, "playerScore9": 0, "playerScore10": 0, "playerScore11": 0}, "needVisionPings": 0, "neutralMinionsKilled": 0, "nexusKills": 0, "nexusLost": 0, "nexusTakedowns": 1, "objectivesStolen": 0, "objectivesStolenAssists": 0, "onMyWayPings": 3, "participantId": 10, "pentaKills": 0, "perks": {"statPerks": {"defense": 5001, "flex": 5008, "offense": 5008}, "styles": [{"description": "primaryStyle", "selections": [{"perk": 8229, "var1": 1824, "var2": 0, "var3": 0}, {"perk": 8226, "var1": 250, "var2": 437, "var3": 0}, {"perk": 8210, "var1": 16, "var2": 0, "var3": 0}, {"perk": 8237, "var1": 696, "var2": 0, "var3": 0}], "style": 8200}, {"description": "subStyle", "selections": [{"perk": 8345, "var1": 3, "var2": 0, "var3": 194}, {"perk": 8347, "var1": 0, "var2": 0, "var3": 0}], "style": 8300}]}, "physicalDamageDealt": 5188, "physicalDamageDealtToChampions": 1313, "physicalDamageTaken": 11179, "placement": 0, "playerAugment1": 0, "playerAugment2": 0, "playerAugment3": 0, "playerAugment4": 0, "playerAugment5": 0, "playerAugment6": 0, "playerSubteamId": 0, "positionAssignedByMatchmaking": "UTILITY", "profileIcon": 5430, "pushPings": 0, "puuid": "f-rlectDTBi667BkmMQcuDBZf93Dc_yuNlMWbW8_GAHdxuEZEqsnTwJOjwZQRmj4_ccqXHQB4PGg3Q", "quadraKills": 0, "retreatPings": 0, "riotIdGameName": "dipper pines", "riotIdTagline": "him", "role": "SUPPORT", "roleBoundItem": 1208, "selectedRolePreferences": "UTILITY.FILL_PRIMARY.FILL.UNSELECTED.FILL", "sightWardsBoughtInGame": 0, "spell1Casts": 62, "spell2Casts": 84, "spell3Casts": 53, "spell4Casts": 11, "subteamPlacement": 0, "summoner1Casts": 6, "summoner1Id": 4, "summoner2Casts": 7, "summoner2Id": 14, "summonerId": "5g1ZZ5jSO3MJlgsWSBrlFyGR9hK2MPhQ4WYIFo3tDCtjdfkVteCKQ5a_uA", "summonerLevel": 617, "summonerName": "", "teamEarlySurrendered": false, "teamIGNBSurrendered": false, "teamId": 200, "teamPosition": "UTILITY", "timeCCingOthers": 54, "timePlayed": 1712, "totalAllyJungleMinionsKilled": 0, "totalDamageDealt": 87695, "totalDamageDealtToChampions": 23519, "totalDamageShieldedOnTeammates": 0, "totalDamageTaken": 25366, "totalEnemyJungleMinionsKilled": 0, "totalHeal": 5137, "totalHealsOnTeammates": 0, "totalMinionsKilled": 59, "totalTimeCCDealt": 157, "totalTimeSpentDead": 133, "totalUnitsHealed": 1, "tripleKills": 0, "trueDamageDealt": 4932, "trueDamageDealtToChampions": 1036, "trueDamageTaken": 3117, "turretKills": 2, "turretTakedowns": 5, "turretsLost": 1, "unrealKills": 0, "visionClearedPings": 0, "visionScore": 43, "visionWardsBoughtInGame": 0, "wardsKilled": 5, "wardsPlaced": 15, "wasPremadeWithIGNBGameEndCauser": false, "wasPremadeWithSevereTransgressor": false, "wasSevereTransgressor": false, "win": true}], "platformId": "EUW1", "queueId": 440, "teams": [{"bans": [{"championId": 35, "pickTurn": 1}, {"championId": 67, "pickTurn": 2}, {"championId": 800, "pickTurn": 3}, {"championId": 89, "pickTurn": 4}, {"championId": 51, "pickTurn": 5}], "objectives": {"atakhan": {"first": false, "kills": 0}, "baron": {"first": false, "kills": 0}, "champion": {"first": false, "kills": 18}, "dragon": {"first": false, "kills": 0}, "horde": {"first": true, "kills": 3}, "inhibitor": {"first": false, "kills": 0}, "riftHerald": {"first": true, "kills": 1}, "tower": {"first": false, "kills": 1}}, "teamId": 100, "win": false}, {"bans": [{"championId": 157, "pickTurn": 6}, {"championId": 11, "pickTurn": 7}, {"championId": 17, "pickTurn": 8}, {"championId": 7, "pickTurn": 9}, {"championId": -1, "pickTurn": 10}], "objectives": {"atakhan": {"first": false, "kills": 0}, "baron": {"first": true, "kills": 1}, "champion": {"first": true, "kills": 66}, "dragon": {"first": true, "kills": 4}, "horde": {"first": false, "kills": 0}, "inhibitor": {"first": true, "kills": 4}, "riftHerald": {"first": false, "kills": 0}, "tower": {"first": true, "kills": 13}}, "teamId": 200, "win": true}], "tournamentCode": ""}}